[
  {
    "nama_produk": "Panci Listrik Elektrik Cooker Stainless Steel Teflon Cooking Pot rice cooker mini",
    "harga": "47,9RB",
    "link_komisi": "https://s.shopee.co.id/6KzYGq8YRl"
  },
  {
    "nama_produk": "❤❤NEW HEADSET BLUETOOTH TWS INPODS I12 MACARON EARPHONE BLUETOOTH 5.0 WARNA MACARON",
    "harga": "21,9RB",
    "link_komisi": "https://s.shopee.co.id/6Ag84X9Bmk"
  },
  {
    "nama_produk": "Swipe Up Kemeja Batik Pria Modern Slimfit Katun Lengan Panjang Motif Katsura Navy",
    "harga": "204,0RB",
    "link_komisi": "https://s.shopee.co.id/60MhsE9p7j"
  },
  {
    "nama_produk": "Kemeja Koko Printing Pria Lengan Pendek dan Lengan Panjang OXVAL - HAFS",
    "harga": "98,9RB",
    "link_komisi": "https://s.shopee.co.id/5q3HfvASSi"
  },
  {
    "nama_produk": "Hidden Slot Card - Case iPhone With Sliding Door Pocket Casing iPhone X XS 11 12 13 14 15 16 Pro Max",
    "harga": "65,6RB",
    "link_komisi": "https://s.shopee.co.id/5fjrTcB5nh"
  },
  {
    "nama_produk": "BASRENG 1KG Paket Hemat Snack Mix Pedas Original dengan Daun Jeruk",
    "harga": "47,5RB",
    "link_komisi": "https://s.shopee.co.id/5VQRHJBj8g"
  },
  {
    "nama_produk": "HOUGUO 2.8 Meter Kemoceng Microfiber 280cm Tarik Tekuk Panjang Alat Pembersih Langit-Langit Rumah Bisa Di Tekuk Kemoceng Panjang",
    "harga": "22,0RB",
    "link_komisi": "https://s.shopee.co.id/5L7150CMTf"
  },
  {
    "nama_produk": "SAMSUNG A55 5G RAM 8/256GB NEW 100% ORIGINAL FREE ADAPTOR 25W",
    "harga": "5,0JT",
    "link_komisi": "https://s.shopee.co.id/7poM3b2qPA"
  },
  {
    "nama_produk": "[ UNISEX ] Celana Jeans Baggy Pants Gombrong Pria/Wanita Highwaist Wid Leg Oversize Premium Quality",
    "harga": "75,0RB",
    "link_komisi": "https://s.shopee.co.id/7fUvKJwE3s"
  },
  {
    "nama_produk": "Campuran Kacang Segar berbagai jenis 500g / 1KG terdiri dari Kenari / Almond / Gajus / Kismis Hitam / Kismis Emas berkualitas tinggi.",
    "harga": "86,5RB",
    "link_komisi": "https://s.shopee.co.id/7VBVez4758"
  },
  {
    "nama_produk": "Kaos Pria Tulisan One Life Sablon/Gambar Dtf Besar Kaos Distro Pria Baju Pria Gambar Kaos Unisex Dewasa Kaos Pria Lengan Pendek",
    "harga": "25,4RB",
    "link_komisi": "https://s.shopee.co.id/7Ks5Sg4kQ7"
  },
  {
    "nama_produk": "Perdana AXIS Bronet 24Jam 3GB 30hr",
    "harga": "35,0RB",
    "link_komisi": "https://s.shopee.co.id/7AYfGN5Nl6"
  },
  {
    "nama_produk": "8 pcs Parcel Mini Amplop Lebaran Model Tas",
    "harga": "14,6RB",
    "link_komisi": "https://s.shopee.co.id/70FF446165"
  },
  {
    "nama_produk": "CROPTOP LENGAN PANJANG KNIT HORNET LEHER KERAH",
    "harga": "22,0RB",
    "link_komisi": "https://s.shopee.co.id/6pvorl6eR4"
  },
  {
    "nama_produk": "Dasfelix Moscow Ice - Extrait de Parfum - Aroma Fresh Aquatic Apple Citrus | Perfume Minyak Wangi Pria Tahan Lama",
    "harga": "109,0RB",
    "link_komisi": "https://s.shopee.co.id/6fcOfS7Hm3"
  },
  {
    "nama_produk": "URzcolletion -Set Sarko Sarung Dan Baju Koko Pria Modern Motif Terbaru 2026 Premium Katun Adem",
    "harga": "88,5RB",
    "link_komisi": "https://s.shopee.co.id/9AJje2xlhY"
  },
  {
    "nama_produk": "Terlaris Celana Cutbray Celana Panjang Wanita Celana Kantor Celana Kulot Scuba",
    "harga": "26,6RB",
    "link_komisi": "https://s.shopee.co.id/900JRjyP2X"
  },
  {
    "nama_produk": "Basreng Pedas Daun Jeruk/ Original / Balado 100 Gram",
    "harga": "6,3RB",
    "link_komisi": "https://s.shopee.co.id/8pgtFQz2NW"
  },
  {
    "nama_produk": "[ CALISTA ] TOPLES AESTHETIC PREMIUM LILY TOPLES KUE KERING LEBARAN ESTETIK 1 SET ISI 6PCS BPA FREE",
    "harga": "62,5RB",
    "link_komisi": "https://s.shopee.co.id/8fNT37zfiV"
  },
  {
    "nama_produk": "Kurma Ajwa Premium Al Madina Kaleng 1 Kg Original 100%",
    "harga": "73,1RB",
    "link_komisi": "https://s.shopee.co.id/8V42qp0J3U"
  },
  {
    "nama_produk": "Kahf Eau de Toilette 35 ml Parfum Pria EDT Pewangi",
    "harga": "81,4RB",
    "link_komisi": "https://s.shopee.co.id/8KkceW0wOT"
  },
  {
    "nama_produk": "Folding Sofa bed By Vassa sofa / Sofabed Minimalist",
    "harga": "849,0RB",
    "link_komisi": "https://s.shopee.co.id/8ARCSD1ZjS"
  },
  {
    "nama_produk": "TNW A37 Wireless Microphone 2-In-1 Clip On Mic Magnetic Mikrofon HP Plug & Play Dual Lavalier Microphone with Charging Case",
    "harga": "249,5RB",
    "link_komisi": "https://s.shopee.co.id/807mFu2D4R"
  },
  {
    "nama_produk": "kue kering NASTAR, KASTENGEL, PUTRI SALJU, KUE KACANG MINI UKURAN TOPLES 250GR ALGHA",
    "harga": "18,0RB",
    "link_komisi": "https://s.shopee.co.id/AUp7EUsgzw"
  },
  {
    "nama_produk": "[GET 2 PCS] Bundle Cool Wootah Extrait de parfum + Eau de Parfum Parfum Pria Tahan lama 100ML",
    "harga": "141,2RB",
    "link_komisi": "https://s.shopee.co.id/AKVh2BtKKv"
  },
  {
    "nama_produk": "Laptop Lenovo Intel Core i5 / i7 RAM 8GB / 16GB SSD 256GB / 500GB windows 10 / 11 - siap pakai",
    "harga": "1,3JT",
    "link_komisi": "https://s.shopee.co.id/AACGpstxfu"
  },
  {
    "nama_produk": "M&T Ip 15 Plus IBOX 128 GB 256 GB",
    "harga": "13,0JT",
    "link_komisi": "https://s.shopee.co.id/9zsqdZub0t"
  },
  {
    "nama_produk": "RAIYA DRESS Gamis silk premium busui jumbo terbaru",
    "harga": "160,6RB",
    "link_komisi": "https://s.shopee.co.id/9pZQRGvELs"
  },
  {
    "nama_produk": "BRAVEKIDS FASHION SETELAN ANAK LAKI LAKI RUGBY TEES KATUN 24S UMUR 1-5 TAHUN T-SHIRT & CELANA COTTON DRILL KARGO COMBED NYAMAN & GAYA SIZE S-M-L BAHAN PAKAIAN ONE SET BAJU ANAK LAKI LAKI COTTON COMBED 24S SABLON PLASTISOL",
    "harga": "66,8RB",
    "link_komisi": "https://s.shopee.co.id/9fG0Exvrgr"
  },
  {
    "nama_produk": "VELOCUST - Celana Panjang Jeans Loosefit Loose Pants Denim Washing",
    "harga": "147,5RB",
    "link_komisi": "https://s.shopee.co.id/9Uwa2ewV1q"
  },
  {
    "nama_produk": "Apple iPhone 17 Pro Max 256GB 512GB 1TB 2TB Garansi Resmi IBox / Digimap / GDN",
    "harga": "26,6JT",
    "link_komisi": "https://s.shopee.co.id/9Kd9qLx8Mp"
  },
  {
    "nama_produk": "[ BISA COD ] KACAMATA MINUS PHOTOCROMIC KEKINIAN 2189 KACAMATA PLUS / MINUS",
    "harga": "60,0RB",
    "link_komisi": "https://s.shopee.co.id/1BHS7LSDwG"
  },
  {
    "nama_produk": "Tali Gantungan HP Universal | Liontin Bintang & Awan Putih yang Lucu | Pakai di Casing Ponsel B112",
    "harga": "10,6RB",
    "link_komisi": "https://s.shopee.co.id/10y1v2SrHF"
  },
  {
    "nama_produk": "Leora Blouse Knit / Blouse Pita Kekinian",
    "harga": "24,0RB",
    "link_komisi": "https://s.shopee.co.id/qebijTUcE"
  },
  {
    "nama_produk": "IP 12 SERIES SECOND INTER 64GB/128GB",
    "harga": "3,5JT",
    "link_komisi": "https://s.shopee.co.id/gLBWQU7xD"
  },
  {
    "nama_produk": "Jersey Anak Number Series Jersey Roblox Anak Mini Movers Jersey Casual",
    "harga": "100,0RB",
    "link_komisi": "https://s.shopee.co.id/W1lK7UlIC"
  },
  {
    "nama_produk": "LUBABA HENNA/ INAI KUKU HALA SAH SHOLAT WARNA TAHAN LAMA/ Henna kuku halal",
    "harga": "10,5RB",
    "link_komisi": "https://s.shopee.co.id/LiL7oVOdB"
  },
  {
    "nama_produk": "Arabell Sultan Gamis Lebaran Anak Babidoll Mix Chantily Baju Dress Pesta Motif Bunga Terbaru Muslim Syari Mewah Remaja Bahan Nyaman",
    "harga": "165,5RB",
    "link_komisi": "https://s.shopee.co.id/BOuvVW1yA"
  },
  {
    "nama_produk": "IP 15/15 PLUS 256GB\\128GB SECOND MULUSFULLSET100% BERGARANSI",
    "harga": "7,0JT",
    "link_komisi": "https://s.shopee.co.id/15UjCWfJ9"
  },
  {
    "nama_produk": "BASRENG SULTAN BANDUNG - 500Gr",
    "harga": "27,8RB",
    "link_komisi": "https://s.shopee.co.id/2VmphnN9Ee"
  },
  {
    "nama_produk": "Celana Jeans Panjang Pria Gombrong Skena Wide Leg Wisker Retro Premium",
    "harga": "51,3RB",
    "link_komisi": "https://s.shopee.co.id/2LTPVUNmZd"
  },
  {
    "nama_produk": "Sajadah Tebal Empuk Motif Turki Ukuran Besar Bahan Busa Bulu Halus Lembut Anti Slip Lantai",
    "harga": "51,7RB",
    "link_komisi": "https://s.shopee.co.id/2B9zJBOPuc"
  },
  {
    "nama_produk": "[NEW] Braven Extreme Series Extrait De Parfum 100ML - Parfum Pria Wangi Tahan Lama - Long Lasting - Extrait Parfum - Aqua / Tobaco / Leather / Musk / Oud / Dream Water / Dark Imagination",
    "harga": "68,8RB",
    "link_komisi": "https://s.shopee.co.id/20qZ6sP3Fb"
  },
  {
    "nama_produk": "WARDAH Ombre Glasting Liquid Lip + Matte Lip Cream -Lip-Stain-Lipgloss-Lipstik-Lip Matte-Lipcream-Lip Cream- Glossy Longlasting Waterproof Tahan Lama - Glaze Lip - Liptint Anak Sekolah - Makeup",
    "harga": "130,7RB",
    "link_komisi": "https://s.shopee.co.id/1qX8uZPgaa"
  },
  {
    "nama_produk": "1 PACK BASO ACI ORI PEDAS INSTAN MANTAP KUAH PREMIUM SPESIAL MURAH BANGET JAJANAN HOTPOT INSTAN SANTAI MAKAN BARENG KELUARGA JAJANAN GRATIS ONGKIR",
    "harga": "10,0RB",
    "link_komisi": "https://s.shopee.co.id/1gDiiGQJvZ"
  },
  {
    "nama_produk": "ONYX MagSafe Tech Case iPhone 13–17 Pro Max | Integrated Stand Design Precision Camera Shield",
    "harga": "109,0RB",
    "link_komisi": "https://s.shopee.co.id/1VuIVxQxGY"
  },
  {
    "nama_produk": "iPhone 12 Pro Max 64GB 128GB 256GB Second ORIGINAL 100% iP 12 / 12 Mini / 12 Pro Mulus Normal Fullset Good CONDITIONS BH 90+",
    "harga": "3,1JT",
    "link_komisi": "https://s.shopee.co.id/1LasJeRabX"
  },
  {
    "nama_produk": "Mukena Batik Dewasa Jumbo Dengan Bahan Premium Adem dan Lembut",
    "harga": "61,2RB",
    "link_komisi": "https://s.shopee.co.id/3qIDIFI4X2"
  },
  {
    "nama_produk": "5Pcs Paket Lipstik Matte Cokelat - Lipstik Matte Anti Air Tahan Lama Yang Tidak Luntur, Set Lipstick Velvet Matte, Tidak Menempel Ke Piala.",
    "harga": "31,5RB",
    "link_komisi": "https://s.shopee.co.id/3fyn5wIhs1"
  },
  {
    "nama_produk": "Keiko Cardigan Knit - Cardigan Rajut Wanita // atasan wanita",
    "harga": "37,1RB",
    "link_komisi": "https://s.shopee.co.id/3VfMtdJLD0"
  },
  {
    "nama_produk": "TRIPOD HP DAN KAMERA UNIVERSAL + FREE HOLDER U WEIFENG Tripod mini 3110/3120 handphone hp u holder tripod konten kreator tongsis tripod bluetooth",
    "harga": "58,5RB",
    "link_komisi": "https://s.shopee.co.id/3LLwhKJyXz"
  },
  {
    "nama_produk": "Mukena Dewasa 2in1 Silk Mysha Armanie",
    "harga": "75,0RB",
    "link_komisi": "https://s.shopee.co.id/3B2WV1Kbsy"
  },
  {
    "nama_produk": "LW—Celana Jeans Pria celana panjang pria Korean style celana kulot pria celana jeans cowok keren boyfriend gombrang straight jeans baggy pants celana denim pants celana cowo oversize Loose pants",
    "harga": "185,0RB",
    "link_komisi": "https://s.shopee.co.id/30j6IiLFDx"
  },
  {
    "nama_produk": "Mukena Dewasa jumbo adem terbaru Daily Aisyah Sutra Velvet Renda ziper premium mewah 2024",
    "harga": "149,0RB",
    "link_komisi": "https://s.shopee.co.id/2qPg6PLsYw"
  },
  {
    "nama_produk": "ARDELITA - Yunna 3IN1 Set Korean Style Hijab OOTD Remaja Wanita Dewasa Keren Kekinian SetRok Terbaru Untuk Outfit Gaya Korea | Vest Flannel Premium | SET BAJU WANITA 2IN1 | SET ROK 3IN1 | ORIGINAL LABEL",
    "harga": "90,0RB",
    "link_komisi": "https://s.shopee.co.id/2g6Fu6MVtv"
  },
  {
    "nama_produk": "Kacamata Minus -1 -2 -3 -4 -5 -6 Fashion Korea Anti Blue Light Anti Radiasi Smartphone Dan Laptop Model Cat Eye",
    "harga": "21,9RB",
    "link_komisi": "https://s.shopee.co.id/5AnashCzpQ"
  },
  {
    "nama_produk": "RJP Jersey Retro Local Pride Famous Series Number 03 Warna Biru Streatwear Rugby",
    "harga": "66,0RB",
    "link_komisi": "https://s.shopee.co.id/50UAgODdAP"
  },
  {
    "nama_produk": "Sweater Rajut Wanita Pria Unisex Knitwear Boxy Skena Sport 01",
    "harga": "99,0RB",
    "link_komisi": "https://s.shopee.co.id/4qAkU5EGVO"
  },
  {
    "nama_produk": "ATASAN OUTER KARDIGAN AMEEZA PANJANG -+128cm",
    "harga": "65,0RB",
    "link_komisi": "https://s.shopee.co.id/4frKHmEtqN"
  },
  {
    "nama_produk": "Promo Exclusive Original HIGHMORE HEXA Tas Selempang Pria Multifungsi Clutchbag Handbag Waterproof",
    "harga": "40,4RB",
    "link_komisi": "https://s.shopee.co.id/4VXu5TFXBM"
  },
  {
    "nama_produk": "HP Nokia 130/2023 Garansi Toko 1 Bulan Murah",
    "harga": "159,0RB",
    "link_komisi": "https://s.shopee.co.id/4LETtAGAWL"
  },
  {
    "nama_produk": "TRENDING BELI 1 DAPAT 2 PARFUM VANILLA | Long Lasting Parfum wanita tahan lama 24 jam - Parfum cewek Terlaris - Parfum Viral - 35ml Eau De Parfume",
    "harga": "9,0RB",
    "link_komisi": "https://s.shopee.co.id/4Av3grGnrK"
  },
  {
    "nama_produk": "Jersey Anak Number 66 Jersey Retro Casual Anak Jersey Full Printing Bahan Dryfit Brazil Vintage",
    "harga": "31,0RB",
    "link_komisi": "https://s.shopee.co.id/40bdUYHRCJ"
  },
  {
    "nama_produk": "Lavio Sepatu Pria Wanita Unisex Safety Boots High Premium Quality Axel Booster Mood Hiking Proyek Outdoor Touring",
    "harga": "285,0RB",
    "link_komisi": "https://s.shopee.co.id/60MhsE9p8i"
  },
  {
    "nama_produk": "IP 14 PLUS SECOND INTER 128GB/256GB",
    "harga": "5,4JT",
    "link_komisi": "https://s.shopee.co.id/6Ag84X9Bnl"
  },
  {
    "nama_produk": "Baju Koko Couple Ayah Anak Laki Laki Bahan Toyobo Import Terbaru 2026 Warna Mahogany Burgundy Denim Motif Bordir",
    "harga": "66,5RB",
    "link_komisi": "https://s.shopee.co.id/6KzYGq8YSo"
  },
  {
    "nama_produk": "Kids Jersey Number 03 Jersey Anak Unisex Jersey Olahraga Anak Casual",
    "harga": "31,0RB",
    "link_komisi": "https://s.shopee.co.id/6VIyT97v7r"
  },
  {
    "nama_produk": "GOLDEN Hampers Lebaran Mangkok Set PREMIUM Hampers Mangkok Piring Lebaran Idul Fitri Parcel Ramadan Parcel Handuk Lebaran",
    "harga": "99,9RB",
    "link_komisi": "https://s.shopee.co.id/5L7150CMUe"
  },
  {
    "nama_produk": "Garansi 24 Bulan | iPhone 14 Plus/Pro Max 128/256GB |Second Inter | Original Inter | BH 100% | Fullset Mulus",
    "harga": "5,2JT",
    "link_komisi": "https://s.shopee.co.id/5VQRHJBj9h"
  },
  {
    "nama_produk": "Kaos Polo Shirt Pria, CR0 Hitam Lengan Pendek Q.Bee",
    "harga": "64,0RB",
    "link_komisi": "https://s.shopee.co.id/5fjrTcB5ok"
  },
  {
    "nama_produk": "QUDAMAH | Thobe Ahsan Model Jubah Saudi Pria Lengan Panjang Polos Non-manset Type Kancing Snap Premium Dengan Kerah Tegak Haramain Bahan Niagara / Picasso Warna Putih, Hitam, Navy, Creamy Grey, Coksu, BW Putih Tulang Reguler - BIG SIZE Jumbo",
    "harga": "212,0RB",
    "link_komisi": "https://s.shopee.co.id/5q3HfvASTn"
  },
  {
    "nama_produk": "Gelas Blender Miyako Kaca 1 Liter BL 102 GS / Gelasnya saja / Gelas Blender Miyako Terlaris",
    "harga": "47,5RB",
    "link_komisi": "https://s.shopee.co.id/7Ks5Sg4kR6"
  },
  {
    "nama_produk": "iPhone 13 256GB/128GB Fullset Second Hand Bergaransi Terpercaya",
    "harga": "4,7JT",
    "link_komisi": "https://s.shopee.co.id/7VBVez4769"
  },
  {
    "nama_produk": "Skateboard Sans Remaja/Skate Board Lapisan Pasir Papan Fullset Kuat SPEEDS LX 028-2808 Sans",
    "harga": "52,8RB",
    "link_komisi": "https://s.shopee.co.id/7fUvKJwE2r"
  },
  {
    "nama_produk": "Hoodie Jaket Zipper [JYB] Oversize SNOOPY ENJOY YOUR SELF (sablon) size M-XXL UNISEX pria&wanita",
    "harga": "87,7RB",
    "link_komisi": "https://s.shopee.co.id/7poM3b2qQF"
  },
  {
    "nama_produk": "LIVI - Scarlett Whitening Extrait De Parfume 30ml - Parfum Wangi Soft Tahan Lama Best Seller by finishshop",
    "harga": "8,8RB",
    "link_komisi": "https://s.shopee.co.id/6fcOfS7Hn2"
  },
  {
    "nama_produk": "Laoshidaishu Koper mini wanita 18 Inch koper kabin USB charger 20 Inch Kapasitas besar 24 Inch koper cup holder 28 Inch",
    "harga": "364,6RB",
    "link_komisi": "https://s.shopee.co.id/6pvorl6eS5"
  },
  {
    "nama_produk": "PROMO HEBAT IP 12/12 MINI 64GB 128GB Second Inter Fullset LCD ORI 100 Good Condition No Minus No Refurbis No Rekondisi No Rijek",
    "harga": "3,0JT",
    "link_komisi": "https://s.shopee.co.id/70FF446178"
  },
  {
    "nama_produk": "OBLO Crop Hoodie Jacket - Jaket Hoodie Crop Zipper Wanita Crop Oversize",
    "harga": "97,0RB",
    "link_komisi": "https://s.shopee.co.id/7AYfGN5NmB"
  },
  {
    "nama_produk": "MOSSDOOM Tas Selempang Wanita Darby Bag Tas Sling Bag Wanita Tas Bahu",
    "harga": "165,0RB",
    "link_komisi": "https://s.shopee.co.id/8fNT37zfjU"
  },
  {
    "nama_produk": "2 Pcs 50 Ribu Kaos Pocket Saku Pria Pilih Warna Semi Katun Premium 24s Lembut COD Simple",
    "harga": "55,0RB",
    "link_komisi": "https://s.shopee.co.id/qebihykqW"
  },
  {
    "nama_produk": "LIGE Jam Tangan Pintar Asli Bluetooth Tahan Air Layar Sentuh Penuh Jam Tangan Pintar Pria Olahraga Kebugaran untuk Android & IOS Gelang Pintar Smartwatch Men",
    "harga": "359,0RB",
    "link_komisi": "https://s.shopee.co.id/gLBWOzOBV"
  },
  {
    "nama_produk": "RUN.CO Celana Stripe Flowy Kulot Rayon Viscose Wanita Motif Salur",
    "harga": "43,5RB",
    "link_komisi": "https://s.shopee.co.id/1BHS7JxUAc"
  },
  {
    "nama_produk": "Roslina Mukena Jaguar Emboss Silky Premium Jumbo Mewah",
    "harga": "155,0RB",
    "link_komisi": "https://s.shopee.co.id/10y1v0y7Vb"
  },
  {
    "nama_produk": "Deathless Gerage Red & Blue T-Shirt Longsleeve Motor Series Atasan Lengan Panjang Unisex",
    "harga": "61,6RB",
    "link_komisi": "https://s.shopee.co.id/BOuvU1ICS"
  },
  {
    "nama_produk": "HEIDI ROK CERUTY SUSUN EMPAT 4 MAXI SKIRT RUFLA RUFFLE REMPEL FULL MIDI TERMURAH EKSKLUSIF PROMOSI DISKON BTCSOLO CERUTI WANITA",
    "harga": "50,1RB",
    "link_komisi": "https://s.shopee.co.id/15UjB1vXR"
  },
  {
    "nama_produk": "BUNDLING 3 ( SOSRENG 250gr + BASRENG PEDAS 250gr + SEBLAK MIX 250gr )",
    "harga": "38,7RB",
    "link_komisi": "https://s.shopee.co.id/W1lK601WY"
  },
  {
    "nama_produk": "Rowling (ka-680) Kacamata Hitam Bingkai Hitam Anti-UV Wanita Import Kacamata Sunglasses Fashion",
    "harga": "11,0RB",
    "link_komisi": "https://s.shopee.co.id/LiL7n0erX"
  },
  {
    "nama_produk": "SAMBAL CUMI PETE/SAMBEL ROA ASAP/CUMI IJO/TERASI/GEPREK/JENGKOL/CABE IJO/by DAPOER SUMEDANG",
    "harga": "25,0RB",
    "link_komisi": "https://s.shopee.co.id/2B9zJ9tg8u"
  },
  {
    "nama_produk": "Yasmen abaya dress bahan marbela anti uv aplikasi payet mutiara abaya umroh anti uv simple mewah elegant",
    "harga": "187,6RB",
    "link_komisi": "https://s.shopee.co.id/20qZ6quJTt"
  },
  {
    "nama_produk": "[NEW] Braven Extreme Series Extrait De Parfum 100ML - Braven Extreme Aqua",
    "harga": "68,8RB",
    "link_komisi": "https://s.shopee.co.id/2VmphlsPT0"
  },
  {
    "nama_produk": "Lemari Plastik / Lemari Pakaian / Laci Plastik Jumbo SSN 5",
    "harga": "90,0RB",
    "link_komisi": "https://s.shopee.co.id/2LTPVSt2nz"
  },
  {
    "nama_produk": "Tango wafer kaleng vanilla + coklat susu 2 x 50 gr isi 2 kaleng & tango wafer kaleng coconut + coklat 2 x 50 gr isi 2 kaleng exp 12/2026",
    "harga": "27,8RB",
    "link_komisi": "https://s.shopee.co.id/1VuIVvwDUq"
  },
  {
    "nama_produk": "PALING HITS-AUDY PANTS-CELANA WANITA-CELANA PANJANG HIGHTWAIST LOOSE PANTS STRIPE-CELANA KULOT TERBARU",
    "harga": "46,9RB",
    "link_komisi": "https://s.shopee.co.id/1LasJcwqpp"
  },
  {
    "nama_produk": "Produsen Rajut Bandung Sweater Cardigan Crop Top Premium Variasi Pita Tali 100% Bahan Akrilik Lembut",
    "harga": "51,0RB",
    "link_komisi": "https://s.shopee.co.id/1qX8uXuwow"
  },
  {
    "nama_produk": "ELZIOSTORE.10 BAJU KOKO PRIA DEWASA LENGAN PENDEK - Koko Muslim Kombinasi Tiga Warna Terbaru Toyobo",
    "harga": "59,0RB",
    "link_komisi": "https://s.shopee.co.id/1gDiiEva9v"
  },
  {
    "nama_produk": "Kacang Mede Oven Super Matang 1Kg Mete Utuh Panggang Mente Roasted Khas Wonogiri",
    "harga": "77,0RB",
    "link_komisi": "https://s.shopee.co.id/3VfMtbobRI"
  },
  {
    "nama_produk": "ORO PANTS - Loose Pants Troures Wanita - Celana Kulot Wanita - Celana Kerja Anti Kusut Bahan Knit Premium",
    "harga": "36,0RB",
    "link_komisi": "https://s.shopee.co.id/3LLwhIpEmH"
  },
  {
    "nama_produk": "Maxy Silk Premium Couple ibu & anak",
    "harga": "100,0RB",
    "link_komisi": "https://s.shopee.co.id/3qIDIDnKlO"
  },
  {
    "nama_produk": "KEMEI KM PG-809A Mesin Alat Cukur Rambut Kumis Jenggot Hair Clipper Electric Professional",
    "harga": "146,3RB",
    "link_komisi": "https://s.shopee.co.id/3fyn5uny6N"
  },
  {
    "nama_produk": "Kursi Lesehan Lipat Sandaran Bantal Jumbo 120KG Sofa Lantai Tatami Empuk Multifungsi Floor Chair Minimalis",
    "harga": "134,1RB",
    "link_komisi": "https://s.shopee.co.id/2qPg6Nr8nE"
  },
  {
    "nama_produk": "NANDA MILLANO sandal flat wanita korean style kekinian sendal tali felicia sol karet anti slip",
    "harga": "93,0RB",
    "link_komisi": "https://s.shopee.co.id/2g6Fu4rm8D"
  },
  {
    "nama_produk": "3 Pack Kacang Kupas | Kacang Tanah Mentah Kupas 250 GRAM/ BUNGKUS",
    "harga": "34,9RB",
    "link_komisi": "https://s.shopee.co.id/3B2WUzps7K"
  },
  {
    "nama_produk": "Napusha - Kaffa Outer | tunic brukat | Outer kondangan | Kebaya Wisuda | Kebaya Modern | Brukat Blouse | Outer lebaran | Tunic Katbor",
    "harga": "160,0RB",
    "link_komisi": "https://s.shopee.co.id/30j6IgqVSJ"
  },
  {
    "nama_produk": "GiantMeng - Lemari Lipat Plastik 3-6 Susun Portable + Roda | Rak Serbaguna Muat Banyak",
    "harga": "109,0RB",
    "link_komisi": "https://s.shopee.co.id/4qAkU3jWjg"
  },
  {
    "nama_produk": "Grass Sabik - Promo 1 Paket Isi 3 Pcs Polo Shirt Polos Terkeren T-Shirt Baju Santai Baju Kerah Brand",
    "harga": "135,4RB",
    "link_komisi": "https://s.shopee.co.id/4frKHkkA4f"
  },
  {
    "nama_produk": "Inere Dress Gamis Mewah Elegan Terbaru 2025 A-Line Ceruty",
    "harga": "159,0RB",
    "link_komisi": "https://s.shopee.co.id/5AnasfiG3m"
  },
  {
    "nama_produk": "Kurma Ruthob Merk Luxury Dates Ruthab Kurma Muda Libiya Isi -+ 1 Kg Asli Libya Grosir Murah Fresh",
    "harga": "51,8RB",
    "link_komisi": "https://s.shopee.co.id/50UAgMitOl"
  },
  {
    "nama_produk": "Setelan 3 in 1 Anak Perempuan Tanpa Hijab Terbaru Usia 3-12 Tahun",
    "harga": "152,6RB",
    "link_komisi": "https://s.shopee.co.id/4Av3gpm45c"
  },
  {
    "nama_produk": "RJP SUPPLY Jersey OnePiece Full Printing Sublimasi Series Anime OnePiece Luffy / baju onepiece / jersey onepiece / kaos onepiece / NFL / rugby",
    "harga": "85,0RB",
    "link_komisi": "https://s.shopee.co.id/40bdUWmhQb"
  },
  {
    "nama_produk": "baju koko pria baju koko muslim baju koko kombinasi batik dan bordil lengan pendek",
    "harga": "62,5RB",
    "link_komisi": "https://s.shopee.co.id/4VXu5RknPi"
  },
  {
    "nama_produk": "Almagadon - Jeans Cutbray Highwaist Wanita Celana Jeans Wanita Celana Cutbray Stretch Highwaist",
    "harga": "50,4RB",
    "link_komisi": "https://s.shopee.co.id/4LETt8lQkh"
  },
  {
    "nama_produk": "Kaos Pria Kerah Shanghai Saku Polet Lengan Garis Sleting - Kaos Pria Distro Premium Motif Model Zipper Terbaru",
    "harga": "80,0RB",
    "link_komisi": "https://s.shopee.co.id/6Ag84VeS24"
  },
  {
    "nama_produk": "PARFUM UNISEX 30 ML AROMA UNISEX- PARFUM UNISEX-INSPIRED – EAU DE TOILETTE 30 ML",
    "harga": "20,0RB",
    "link_komisi": "https://s.shopee.co.id/60MhsCf5N3"
  },
  {
    "nama_produk": "Wadimor - Sarung Bordir Motif Mozaik Timbul Katun Hitam Pintu Aceh Pria Dewasa",
    "harga": "185,0RB",
    "link_komisi": "https://s.shopee.co.id/6VIyT7dBMA"
  },
  {
    "nama_produk": "Servodio - Artemis Fans Edition Hitam Polos - Sepatu Sneakers Running Gym Shoes Fashion",
    "harga": "105,5RB",
    "link_komisi": "https://s.shopee.co.id/6KzYGodoh9"
  },
  {
    "nama_produk": "House Of We Kala Tas Hobo Tote BAG Wanita VENY Totebag Lucu",
    "harga": "88,5RB",
    "link_komisi": "https://s.shopee.co.id/5VQRHHgzO0"
  },
  {
    "nama_produk": "ALLUNA - Mukena Dewasa Mewah Santorini Silk 2in1 Zhafira Series",
    "harga": "263,0RB",
    "link_komisi": "https://s.shopee.co.id/5L714yhciz"
  },
  {
    "nama_produk": "jasko pria jasko bordir jasko bahan adem",
    "harga": "240,0RB",
    "link_komisi": "https://s.shopee.co.id/5q3Hftfii6"
  },
  {
    "nama_produk": "Tv android 24 inch smart tv 17 Inch 4K Android TVWith Youtube/Google/Netflix/WIFI 5 Tahun Garansi",
    "harga": "665,3RB",
    "link_komisi": "https://s.shopee.co.id/5fjrTagM35"
  },
  {
    "nama_produk": "PROMO RAMADHAN SALE TERBARU JEANS PRIA PANJANG NAOMI SOFT JEANS LEMBUT DAN STREECT/MELAR BISA COD 27-32",
    "harga": "97,0RB",
    "link_komisi": "https://s.shopee.co.id/7VBVexZNKS"
  },
  {
    "nama_produk": "Celana panjang kasual pria training pria celana olahraga pria celana gombrong pria celana korean style pria celana putih pria celana kulot pria loose pants hitam celana pria baju couple pasangan kekinian baru",
    "harga": "89,0RB",
    "link_komisi": "https://s.shopee.co.id/7Ks5Sea0fR"
  },
  {
    "nama_produk": "SARUNG BHS CLASIK SONGKET SSJ/SSK/SSB/SSA/SSF KUALITAS GOLD (ORIGINAL)",
    "harga": "575,0RB",
    "link_komisi": "https://s.shopee.co.id/7poM3ZY6eY"
  },
  {
    "nama_produk": "Mukena Traveling Terbaru Mini Pouc 2in1 Laser Cut Motif Bahan Katun Micro Premium Free Tasbih",
    "harga": "58,5RB",
    "link_komisi": "https://s.shopee.co.id/7fUvrGYjzX"
  },
  {
    "nama_produk": "tumbler minum tumbler aesthetic tumbler stainless aesthetic tumbler estetik aesthetic 750ml",
    "harga": "60,0RB",
    "link_komisi": "https://s.shopee.co.id/6pvorjbugO"
  },
  {
    "nama_produk": "Fortisse Mattress Busa Anti-noda High Density Foam - Garansi 15 Tahun High Quality",
    "harga": "354,8RB",
    "link_komisi": "https://s.shopee.co.id/6fcOfQcY1N"
  },
  {
    "nama_produk": "BENHILL Taqwa Koko Bordir \"RAFFI AHMAD\" Pria Pendek Navy-Black-Off White 2613-58-59",
    "harga": "212,4RB",
    "link_komisi": "https://s.shopee.co.id/7AYfGLae0U"
  },
  {
    "nama_produk": "Kacang Mete Panggang 1 Kg Mede Goreng Utuh Renyah Mente Matang Wonogiri",
    "harga": "65,0RB",
    "link_komisi": "https://s.shopee.co.id/70FF42bHLT"
  },
  {
    "nama_produk": "HIJAB PARIS JADUL SEGIEMPAT | ORI VARIZHA | PARIS VARIZHA",
    "harga": "14,0RB",
    "link_komisi": "https://s.shopee.co.id/8pgtFPUIcq"
  },
  {
    "nama_produk": "Milmode - Dress Anak Karin (6 Bulan - 6 Tahun)",
    "harga": "22,9RB",
    "link_komisi": "https://s.shopee.co.id/8fNT36Uvxp"
  },
  {
    "nama_produk": "Baju Koko Couple Ayah Anak Lengan 3/4 Toyobo Kurta Elegan Atasan Modern",
    "harga": "68,0RB",
    "link_komisi": "https://s.shopee.co.id/9AJje1T1ww"
  },
  {
    "nama_produk": "Gamis abaya anak tali serut pinggang 2-12 tahun bahan jersey adem dan nyaman set hijab",
    "harga": "51,8RB",
    "link_komisi": "https://s.shopee.co.id/900JRiTfHv"
  },
  {
    "nama_produk": "iPh one 12 PROMAX 128GB/256GB GOOD CONDITION LIKE NEW BERGARANSI",
    "harga": "5,4JT",
    "link_komisi": "https://s.shopee.co.id/8ARCSBWpym"
  },
  {
    "nama_produk": "Couple gamis pasangan muslim kekinian reline batik irfana up to ld 120 jumbo",
    "harga": "100,0RB",
    "link_komisi": "https://s.shopee.co.id/807mFsXTJl"
  },
  {
    "nama_produk": "En-ji Monhi Shoulderbag",
    "harga": "296,1RB",
    "link_komisi": "https://s.shopee.co.id/8V42qnVZIs"
  },
  {
    "nama_produk": "Jersey Anak Perempuan Series Pinky Jersey Number Full Printing Jersey Streetwear",
    "harga": "31,0RB",
    "link_komisi": "https://s.shopee.co.id/8KkceUWCdr"
  },
  {
    "nama_produk": "Qwertylife Workshirt Boxy Zipper Engginers Black",
    "harga": "129,0RB",
    "link_komisi": "https://s.shopee.co.id/AACGprPDvE"
  },
  {
    "nama_produk": "CELANA SAM PRIA",
    "harga": "80,3RB",
    "link_komisi": "https://s.shopee.co.id/9zsqdYPrGD"
  },
  {
    "nama_produk": "AS Inara bags - tas selempang wanita terbaru",
    "harga": "32,0RB",
    "link_komisi": "https://s.shopee.co.id/AUp7ETNxFK"
  },
  {
    "nama_produk": "Baju muslim pria kemko sultan embos original kancing snap import",
    "harga": "165,0RB",
    "link_komisi": "https://s.shopee.co.id/AKVh2AOaaJ"
  },
  {
    "nama_produk": "kaos polo pria bordir kaos kerah pria Kemeja Pria Lengan Pendek kaos polos kaos import Kapas T-shirt",
    "harga": "127,5RB",
    "link_komisi": "https://s.shopee.co.id/9Uwa2dRlHA"
  },
  {
    "nama_produk": "Gamis Laura Anak Terbaru Gamis Couple Mom & Kids Dress Rompi Knit Pita Baju Perempuan Trendy",
    "harga": "100,0RB",
    "link_komisi": "https://s.shopee.co.id/9Kd9qKSOc9"
  },
  {
    "nama_produk": "Jersey Mini Movers Anak Series Roblox Jersey Bahan Dryfit Brazil Full Printing Jersey Anak Unisex",
    "harga": "31,0RB",
    "link_komisi": "https://s.shopee.co.id/9pZQRFQUbG"
  },
  {
    "nama_produk": "Cokelat Cube SILVER QUU Isi 40 Pcs / Cokelat Kubus / Cokelat 1 Box",
    "harga": "15,0RB",
    "link_komisi": "https://s.shopee.co.id/9fG0EwR7wF"
  },
  {
    "nama_produk": "Kamila Curly Blouse - Atasan Blouse Wanita Rajut Premium",
    "harga": "70,0RB",
    "link_komisi": "https://s.shopee.co.id/gLBWOzOCW"
  },
  {
    "nama_produk": "IBOX IP 13 PRO IMEI Terdaftar128GB 256GB 512GB Second Bekas Normal TTRS STORE",
    "harga": "3,5JT",
    "link_komisi": "https://s.shopee.co.id/qebihykrZ"
  },
  {
    "nama_produk": "DANYCASE Kipas Angin Portable Mini Tangan Kecil Turbo - Baterai Tahan Lama, USB, Murah, Cepat Angin, Cocok untuk Travel, Kantor, Sekolah dan Aktivitas Luar Ruangan",
    "harga": "57,8RB",
    "link_komisi": "https://s.shopee.co.id/10y1v0y7Wc"
  },
  {
    "nama_produk": "Gamis Lebaran 2026 Model Gamis Terbaru Aruna Ceruty Printing Dress Wanita Kondangan Simple Elegan",
    "harga": "196,0RB",
    "link_komisi": "https://s.shopee.co.id/1BHS7JxUBf"
  },
  {
    "nama_produk": "Aolon GTS 3 Jam Tangan Smartwatch Tipis Original 41mm Amoled AOD Ultra-thin Whatsapp Bluetooth Telepon Detak Jantung Olahraga Kesehatan VS Watch 5 Active",
    "harga": "405,0RB",
    "link_komisi": "https://s.shopee.co.id/15UjB1vYS"
  },
  {
    "nama_produk": "Fleco Super X-Bass Speaker karaoke Bluetooth fleco Super Bass",
    "harga": "249,9RB",
    "link_komisi": "https://s.shopee.co.id/BOuvU1IDV"
  },
  {
    "nama_produk": "Mukena Dewasa Khodijah Mukenah Khadijah Jumbo Premium",
    "harga": "50,2RB",
    "link_komisi": "https://s.shopee.co.id/LiL7n0esY"
  },
  {
    "nama_produk": "Celana jeans pria panjang Baggy jeans celana jeans pria loose celana jeans ovesize gombrong",
    "harga": "119,9RB",
    "link_komisi": "https://s.shopee.co.id/W1lK601Xb"
  },
  {
    "nama_produk": "(Ready) Parcel Lebaran 2026 Isian Campur Hampers Idul Fitri Hari Guru Natal",
    "harga": "89,6RB",
    "link_komisi": "https://s.shopee.co.id/20qZ6quJUu"
  },
  {
    "nama_produk": "Terlaria Rok Rimple Susun 3 Import Premium Bahan Premium Bangkok",
    "harga": "47,0RB",
    "link_komisi": "https://s.shopee.co.id/2B9zJ9tg9x"
  },
  {
    "nama_produk": "100% Asli Samsung SmartWatch XS 11 PRO MAX Gps NFC IP68 Waterproof Bluetooth Call Jam Smartwatch Wanita Pria Monitor Detak Jantung Tekanan Darah wireless charging Dan Ganti Wallpapper Jam Tangan Wanita Jam Tangan Couple Jam Tangan Digital Wanita",
    "harga": "142,5RB",
    "link_komisi": "https://s.shopee.co.id/2LTPVSt2p0"
  },
  {
    "nama_produk": "ROK BROKAT BRUKAT DEWASA TERMURAH KATBOL",
    "harga": "63,9RB",
    "link_komisi": "https://s.shopee.co.id/2VmphlsPU3"
  },
  {
    "nama_produk": "Boneka Fluffy Imut Dengan Rantai Warna - Gantungan HP & Tas, Hadiah Lucu Terpopuler",
    "harga": "15,0RB",
    "link_komisi": "https://s.shopee.co.id/1LasJcwqqq"
  },
  {
    "nama_produk": "Lavio Sepatu Pria Safety Boots High Original Premium Quality Gibson Booster Mood Hiking Proyek Outdoor Touring Trekking Best Seller",
    "harga": "285,0RB",
    "link_komisi": "https://s.shopee.co.id/1VuIVvwDVt"
  },
  {
    "nama_produk": "MINYAK GORENG ROSE BRAND 2L / 1L",
    "harga": "52,5RB",
    "link_komisi": "https://s.shopee.co.id/1gDiiEvaAw"
  },
  {
    "nama_produk": "NAGITA gamis by Daily,ukthi,gaun, Lebaran, bahan, crinkel, Airflow. gamis, Pita, mewah",
    "harga": "104,5RB",
    "link_komisi": "https://s.shopee.co.id/1qX8uXuwpz"
  },
  {
    "nama_produk": "iPhone 15/15 PLUS 512GB/256GB/128GB SECOND ORIGINAL Fullset",
    "harga": "6,8JT",
    "link_komisi": "https://s.shopee.co.id/3LLwhIpEnI"
  },
  {
    "nama_produk": "basreng keripik/basreng bulat/basreng koin Renyah pedas daun jeruk bumbu melimpah",
    "harga": "30,0RB",
    "link_komisi": "https://s.shopee.co.id/3VfMtbobSL"
  },
  {
    "nama_produk": "Kipas Angin USB Turbo Kipas Mini Digital Display Handheld Fan Kipas Angin Mini Portable High-speed Mini Kipas Tangan 15000RPM Kipas Strong Wind 120 Gear Wind Digital Display Adjustable",
    "harga": "31,9RB",
    "link_komisi": "https://s.shopee.co.id/3fyn5uny7O"
  },
  {
    "nama_produk": "Mukena Dewasa Santorini Silk 2in1 Almeera",
    "harga": "75,0RB",
    "link_komisi": "https://s.shopee.co.id/3qIDIDnKmR"
  },
  {
    "nama_produk": "iPhone 16 /16 Plus Second Original iPhone 16 Second 512GB 256GB 128GB Mulus",
    "harga": "6,4JT",
    "link_komisi": "https://s.shopee.co.id/2g6Fu4rm9E"
  },
  {
    "nama_produk": "Zeintin - Baju Koko Pria Dewasa Koko Pria Terbaru Lengan Pendek Katun Toyobo Best Quality AT",
    "harga": "83,9RB",
    "link_komisi": "https://s.shopee.co.id/2qPg6Nr8oH"
  },
  {
    "nama_produk": "Denim Celana Jeans Pria Celana Reguler Fit Pria Jeans Cowok Dewasa Jeans Jumbo Korean Style Straight Pants Hitam Biru Premium Kekinian Panjang Celana Longgar",
    "harga": "71,9RB",
    "link_komisi": "https://s.shopee.co.id/30j6IgqVTK"
  },
  {
    "nama_produk": "Baju Koko Anak Set Sarung Instan Praktis Mudah dipakai ~ Baju Koko Anak ~ Baju Koko Anak Muslim Usia 1-11 tahun",
    "harga": "69,4RB",
    "link_komisi": "https://s.shopee.co.id/3B2WUzps8N"
  },
  {
    "nama_produk": "Samsung Galaxy A56 5G 8/256GB - Awesome Graphite | Galaxy AI | 50MP Camera | 45W Super Fast Charge",
    "harga": "6,3JT",
    "link_komisi": "https://s.shopee.co.id/4frKHkkA5g"
  },
  {
    "nama_produk": "Sarung Instan Dewasa Warna Terbaru Motif Kekinian",
    "harga": "55,3RB",
    "link_komisi": "https://s.shopee.co.id/4qAkU3jWkj"
  },
  {
    "nama_produk": "CELANA DENIM SELVEDGE ACCENT 16 OZ ART SAKHI/ RAW DENIM/SELVEDGE PRIA",
    "harga": "395,0RB",
    "link_komisi": "https://s.shopee.co.id/50UAgMitPm"
  },
  {
    "nama_produk": "DAVIN - Mukena silk jaguar armany silk renda Embos motif",
    "harga": "209,0RB",
    "link_komisi": "https://s.shopee.co.id/5AnasfiG4p"
  },
  {
    "nama_produk": "Paket 6pcs celana pendek wanita hommy rayon premium jumbo | short pants",
    "harga": "54,5RB",
    "link_komisi": "https://s.shopee.co.id/40bdUWmhRc"
  },
  {
    "nama_produk": "Leora Blouse Knit / Blouse Pita Kekinian",
    "harga": "23,2RB",
    "link_komisi": "https://s.shopee.co.id/4Av3gpm46f"
  },
  {
    "nama_produk": "[ UNISEX ] Celana Jeans Whisker Gombrong Highwaist Baggy Pants Skena Wid Leg Oversize Korean Style Terlaris!!",
    "harga": "79,8RB",
    "link_komisi": "https://s.shopee.co.id/4LETt8lQli"
  },
  {
    "nama_produk": "Mukena Sutra Jaguar Remple Street Jumbo Ukuran",
    "harga": "166,9RB",
    "link_komisi": "https://s.shopee.co.id/4VXu5RknQl"
  },
  {
    "nama_produk": "Prays Fashion - Cargo Denim Pasir Putih Highwaist Loose Celana Jeans Wanita Korea(realpict)",
    "harga": "52,8RB",
    "link_komisi": "https://s.shopee.co.id/60MhsCf5O4"
  },
  {
    "nama_produk": "Smartwatch Pria Wanita T800 Ultra IP67 Fitness",
    "harga": "56,0RB",
    "link_komisi": "https://s.shopee.co.id/6Ag84VeS37"
  },
  {
    "nama_produk": "Celana Jeans Pria Celana Panjang Hitam Pria Dewasa Kulot Jeans Murah Denim Jumbo Korean Style Celana Anak Laki Laki Baggy Pants Straight Jeans High Waist Celana Cowok Standar",
    "harga": "62,0RB",
    "link_komisi": "https://s.shopee.co.id/6KzYGodoiA"
  },
  {
    "nama_produk": "Paket Kue lebaran Premium NEW PRIMA JAYA OVAL Isi 6 Varian Rasa Kacang Nastar Putri Salju Murah Toplesan Idul Fitri Hampers Lebaran Ku",
    "harga": "139,8RB",
    "link_komisi": "https://s.shopee.co.id/6VIyT7dBND"
  },
  {
    "nama_produk": "baju dan celana panjang anak laki laki motif 1-5 tahun grosir",
    "harga": "85,0RB",
    "link_komisi": "https://s.shopee.co.id/3LLwhH7zIx"
  },
  {
    "nama_produk": "Toples Lebaran Snack Tray Toples Tempat Kue Cemilan Kotak Penyimpanan Makanan Toples Lebaran Set Nampan Permen Nampan Buah Kacang Kering",
    "harga": "82,6RB",
    "link_komisi": "https://s.shopee.co.id/3B2WUy8cdw"
  },
  {
    "nama_produk": "Kemeja Whispie Atasan Wanita Motif Salur Garis Stripe Slim Fit Body - Wispie Working Baby Shirt - Fitted Shirt Kemeja Salur Kantor Kerja Wanita Lengan Panjang Formal Slimfit - Kemeja Luna Stripe Fitted Motif Salur - Kemeja Kerja Wanita Press Body",
    "harga": "56,7RB",
    "link_komisi": "https://s.shopee.co.id/30j6If9Fyv"
  },
  {
    "nama_produk": "Jaket Pria Casual Terbaru import original slimfit",
    "harga": "133,7RB",
    "link_komisi": "https://s.shopee.co.id/2qPg6M9tJu"
  },
  {
    "nama_produk": "(kartonan)Aneka Kartonan Biskuit Kaleng | Tango Biskuit Kaleng 240 g( EXP DES 2026)",
    "harga": "145,0RB",
    "link_komisi": "https://s.shopee.co.id/2g6Fu3AWet"
  },
  {
    "nama_produk": "KEMEI - Alat Cukur Rambut Elektrik 3in1 Hair Clipper KM 1407 Tanpa Kabel Alat Pencukur Kumis Jenggot",
    "harga": "107,9RB",
    "link_komisi": "https://s.shopee.co.id/5Anase10aO"
  },
  {
    "nama_produk": "Celana Baggy Jeans Retro Wanita Highwaist Loose Korea Style Kulot Acid Grey Panjang 100cm - Beggy Jeans Pants Celana Gombrong Wanita Oversize Retro Hitam",
    "harga": "65,0RB",
    "link_komisi": "https://s.shopee.co.id/50UAgL1dvN"
  },
  {
    "nama_produk": "( PAKET 5 PACK ) detergen sayang bubuk kemasan Rp.5000",
    "harga": "19,8RB",
    "link_komisi": "https://s.shopee.co.id/4qAkU22HGM"
  },
  {
    "nama_produk": "KARDIGAN RAJUT WANITA BAHAN RAJUT TEBAL - BASIC INARA OUTHER KNITE",
    "harga": "39,9RB",
    "link_komisi": "https://s.shopee.co.id/4frKHj2ubL"
  },
  {
    "nama_produk": "Sajadah Turki Premium Tebal / Sejadah antislip bentuk Kubah 70x110cm",
    "harga": "52,0RB",
    "link_komisi": "https://s.shopee.co.id/4VXu5Q3XwK"
  },
  {
    "nama_produk": "VANTEZ - Baju Koko Kurta Embos Basic",
    "harga": "162,0RB",
    "link_komisi": "https://s.shopee.co.id/4LETt74BHJ"
  },
  {
    "nama_produk": "Pashmina Printing Sublime Motif Cashmere Turki Viral Terlaris",
    "harga": "37,8RB",
    "link_komisi": "https://s.shopee.co.id/4Av3go4ocI"
  },
  {
    "nama_produk": "Tas Selempang Wanita Sabrina Sling Bag Wanita Terbaru",
    "harga": "45,0RB",
    "link_komisi": "https://s.shopee.co.id/40bdUV5RxH"
  },
  {
    "nama_produk": "TV Smart Digital TV 17 inch Digital TV 19 inch TV Android 50 inch LED UHD 4K WIFI Youtube/Google Play Dolby Audio",
    "harga": "670,3RB",
    "link_komisi": "https://s.shopee.co.id/1BHS7IGEhk"
  },
  {
    "nama_produk": "UNISEX - Jeans Longgar Boyfriend Gombrong Kulot Loose Style Dewasa Korean Termurah Baggy Pants Cowok Cewek",
    "harga": "110,0RB",
    "link_komisi": "https://s.shopee.co.id/10y1uzGs2j"
  },
  {
    "nama_produk": "LITUAYU SET COUPLE MARBELLA ANTI UV X CERUTY POLOS // DRESS DAN KEMEJA DEWASA PREMIUM By Esha Scarf",
    "harga": "125,5RB",
    "link_komisi": "https://s.shopee.co.id/qebigHVNi"
  },
  {
    "nama_produk": "DONKEY CLOTH- UNISEX Celana Chino Panjang Reguler Standar Premium | Celana Gombrong Bahan Melar",
    "harga": "101,3RB",
    "link_komisi": "https://s.shopee.co.id/gLBWNI8ih"
  },
  {
    "nama_produk": "Stand Holder Phone Kelinci Cute Folding Dekstop Universal Portable",
    "harga": "8,6RB",
    "link_komisi": "https://s.shopee.co.id/W1lK4Im3g"
  },
  {
    "nama_produk": "Daster standar rayon santung 100 rb dapat 4 pcs aneka motif daster kekinian busui bumil rayon santung",
    "harga": "80,0RB",
    "link_komisi": "https://s.shopee.co.id/LiL7lJPOf"
  },
  {
    "nama_produk": "￼Tortton Cardigan Wol Rajut Korean Style Lis Full Mutiara Cardigan High Quality",
    "harga": "135,0RB",
    "link_komisi": "https://s.shopee.co.id/BOuvSK2je"
  },
  {
    "nama_produk": "Baju Koko Anak Laki Laki Sarkoci Setelan Koko Sarung Lengan Pendek Usia 3-10 Tahun Katun Premium",
    "harga": "60,0RB",
    "link_komisi": "https://s.shopee.co.id/15Uj9Kg4d"
  },
  {
    "nama_produk": "Allfarizi | Mukena Travel Mini 2in1 Aliza Katun Motif Free Tas Pouch Terbaru",
    "harga": "51,3RB",
    "link_komisi": "https://s.shopee.co.id/2VmphkBA08"
  },
  {
    "nama_produk": "TWS Wireless Bluetooth Earphone Pro4 Headphones ear buds In-ear Earbuds Hands-free Headset",
    "harga": "25,9RB",
    "link_komisi": "https://s.shopee.co.id/2LTPVRBnL7"
  },
  {
    "nama_produk": "Kemeja Polos Coklat Mahogany Burgundy Pria Lengan Panjang Terlaris | Kemeja Pria Polos Sigaret Premium | Kemeja Polos Burgundy Burgundi",
    "harga": "90,0RB",
    "link_komisi": "https://s.shopee.co.id/2B9zJ8CQg6"
  },
  {
    "nama_produk": "1. Soklin Liquid 16pcs + Royale 10pcs + Free Ember Cantik!",
    "harga": "25,0RB",
    "link_komisi": "https://s.shopee.co.id/20qZ6pD415"
  },
  {
    "nama_produk": "Mukena Katun Voil 2in1 Renda Tile Mewah Adem Nyaman",
    "harga": "77,5RB",
    "link_komisi": "https://s.shopee.co.id/1qX8uWDhM4"
  },
  {
    "nama_produk": "hijab anak bayi bergo pita ( 1-3 tahun ) kerudung anak perempuan terbaru",
    "harga": "25,9RB",
    "link_komisi": "https://s.shopee.co.id/1gDiiDEKh3"
  },
  {
    "nama_produk": "Setulus Signature Kuntum Family Sarimbit Pradory Luxury Motif Batik Set Lebaran Keluarga Couple Gamis Muslim One Set Rok Koko Kemeja Pria Cowok Kurta Dress Pasangan Suami Istri Ayah Ibu Anak Kondangan Mom",
    "harga": "127,8RB",
    "link_komisi": "https://s.shopee.co.id/1VuIVuEy22"
  },
  {
    "nama_produk": "40RIBU DAPAT 3 PCS Broadshot Pendek Katun Casual Santai Nyaman",
    "harga": "42,5RB",
    "link_komisi": "https://s.shopee.co.id/1LasJbFbN1"
  },
  {
    "nama_produk": "Naqiyah - Mukena 2in1 Dewasa Layla Series | Mukena Katun Foil Renda Tule Two tone Atasan Bawahan",
    "harga": "86,3RB",
    "link_komisi": "https://s.shopee.co.id/9AJjdzlmTY"
  },
  {
    "nama_produk": "PAKAIAN MUSLIM ANAK SETELAN BAJU MUSLIM ANAK LAKI LAKI USIA 1-10 TAHUN TERBARU/ SETELAN BAJU KOKO ANAK LAKI LAKI/ SETELAN BAJU KOKO ANAK BAYI/ SETELAN BAJU KOKO ANAK COWOK/ BAJU MUSLIM ANAK COWOK/ SETELAN BAJU NGAJI ANAK COWOK/ BAJU GAMIS ANAK LAKI LAKI",
    "harga": "47,5RB",
    "link_komisi": "https://s.shopee.co.id/900JRgmPoX"
  },
  {
    "nama_produk": "SAKINAH - Jilbab Instan Kerudung Bergo Hamidah Hijab Sport Instan Jersy Korea Size M Harga Murah",
    "harga": "12,0RB",
    "link_komisi": "https://s.shopee.co.id/8pgtFNn39W"
  },
  {
    "nama_produk": "Highwaist Cutbray Street Melar Lentur Celana Wanita Model Era 90an Terbaru Panjang 102",
    "harga": "65,0RB",
    "link_komisi": "https://s.shopee.co.id/8fNT34ngUV"
  },
  {
    "nama_produk": "store.wulandari | mukena silk premium 2in1 MALIKA mukena mewah mukena renda mukena terbaru mukena kekinian mukena luxury mukena motif mukena printing mukena jumbo mukena mewah mukena premium mukena murah mukena nyaman",
    "harga": "122,2RB",
    "link_komisi": "https://s.shopee.co.id/8V42qloJpU"
  },
  {
    "nama_produk": "Sarung Instan Anak Motif Sarwon Usia 1-13 Tahun",
    "harga": "22,9RB",
    "link_komisi": "https://s.shopee.co.id/8KkceSoxAT"
  },
  {
    "nama_produk": "Sandal Pantai Wanita Sandal EVA Tebal Anti-Selip Dalam Ruangan 5CM Sandal Pantai Wanita",
    "harga": "60,2RB",
    "link_komisi": "https://s.shopee.co.id/8ARCS9paVS"
  },
  {
    "nama_produk": "FENTINA Sandal Kodok Wanita Kekinian Sandal Fuji Sandal Baim Wedges Sandal Jelly Wanita Anti-selip",
    "harga": "50,0RB",
    "link_komisi": "https://s.shopee.co.id/807mFqqDqR"
  },
  {
    "nama_produk": "【 Liquidasi – Semua Harus Laku】Kipas Angin Mini Portable Semikonduktor Turbo Kencang 18000RPM Baterai Tahan Lama USB Rechargeable Pendinginan Cepat untuk Outdoor/Camping/Kantor",
    "harga": "76,0RB",
    "link_komisi": "https://s.shopee.co.id/AUp7ERghlw"
  },
  {
    "nama_produk": "Vazeera Gamis Anak Perempuan Cantik Usia 4-12 Tahun – Dress Muslim Marbela Bordir",
    "harga": "165,0RB",
    "link_komisi": "https://s.shopee.co.id/AKVh28hL6v"
  },
  {
    "nama_produk": "KERIPIK BASRENG BULAT BUMBU PEDAS DAUN JERUK 500G TERLARIS TERMURAH CEMILAN VIRAL - TERCIDUK BUMBU BERLIMPAH",
    "harga": "35,9RB",
    "link_komisi": "https://s.shopee.co.id/AACGpphyRu"
  },
  {
    "nama_produk": "Sandal pantai non-slip wanita terbaru dari Baim dengan tebalSandal pantai wanita baru 2025 tebal",
    "harga": "55,0RB",
    "link_komisi": "https://s.shopee.co.id/9zsqdWibmt"
  },
  {
    "nama_produk": "KIDSID Setelan kemeja anak lengan pendek warna Dark Brown + celana chinos usia 1-14 Tahun - One set Baju setelan anak Bahan Katun Import - Setelan Kemeja Anak Laki- laki 1 2 3 4 5 6 7 8 9 10 11 12 13 Tahun - stelan Kemeja anak - OOTD Fashion anak",
    "harga": "70,0RB",
    "link_komisi": "https://s.shopee.co.id/9pZQRDjF7s"
  },
  {
    "nama_produk": "MYKONOS Decant Share All Variant 2ML - 10ML Original 100% Monaco Royale California Glitch Sorrennto",
    "harga": "51,0RB",
    "link_komisi": "https://s.shopee.co.id/9fG0EujsSr"
  },
  {
    "nama_produk": "Leony Dress Rayon Gamis Rayon busui Gamis motif Terbaru Lengan Lonceng Gamis Jumbo",
    "harga": "99,9RB",
    "link_komisi": "https://s.shopee.co.id/9Uwa2bkVnq"
  },
  {
    "nama_produk": "sandal semi sepatu menutup / Sandal Flat Wanita Sepatu wanita fashionable gaya Korea Motif Kait Fashion Sepatu",
    "harga": "70,0RB",
    "link_komisi": "https://s.shopee.co.id/9Kd9qIl98p"
  },
  {
    "nama_produk": "Jubah Pria Dewasa Premium Kancing Sultan - Athowaf Sultan Series",
    "harga": "125,0RB",
    "link_komisi": "https://s.shopee.co.id/6VIyT5vvtI"
  },
  {
    "nama_produk": "1Kg Kacang Bawang Goreng Jumbo Lezat Dan Sehat",
    "harga": "64,5RB",
    "link_komisi": "https://s.shopee.co.id/6KzYGmwZEH"
  },
  {
    "nama_produk": "Erabyan Shoes - Naisha Sepatu Mules Heels Wanita | Hak 3 Cm",
    "harga": "119,6RB",
    "link_komisi": "https://s.shopee.co.id/6Ag84TxCZG"
  },
  {
    "nama_produk": "Celana Panjang Wanita Loose High Waist Jeans Premium - Korean Stayle Jeans Baggy Loose Oversize",
    "harga": "60,0RB",
    "link_komisi": "https://s.shopee.co.id/60MhsAxpuF"
  },
  {
    "nama_produk": "Baju Atasan Crop Top Wanita Terbaru-Crop Top Wanita Korean style-Kaos Crop Top Murah Terbaru",
    "harga": "27,7RB",
    "link_komisi": "https://s.shopee.co.id/5q3HfryTFE"
  },
  {
    "nama_produk": "Khong Guan Biskuit Kaleng Besar 1600g Exp 2027",
    "harga": "75,9RB",
    "link_komisi": "https://s.shopee.co.id/5fjrTYz6aD"
  },
  {
    "nama_produk": "SUNCO 2Liter 4pcs Minyak goreng rendah lemak, jernih, tidak mudah menghitam",
    "harga": "57,9RB",
    "link_komisi": "https://s.shopee.co.id/5VQRHFzjvC"
  },
  {
    "nama_produk": "official Celana Kargo Ukuran Besar untuk Anak Laki-laki Musim Semi Musim Gugur 2025 Celana Kasual Kaki Lurus Baru Celana Anak-anak Trendi dan Keren",
    "harga": "137,1RB",
    "link_komisi": "https://s.shopee.co.id/5L714x0NGB"
  },
  {
    "nama_produk": "Mukena Dewasa Bordir Motif Songket Katun Mikro Premium Jumbo",
    "harga": "112,1RB",
    "link_komisi": "https://s.shopee.co.id/7poM3XqrBg"
  },
  {
    "nama_produk": "khong guan merah 1600g besar orginil, kue biskuit , hock guan gede 1350, dua pilihan sama sama ukuran kaleng gede, kue lebaran legenda.",
    "harga": "98,1RB",
    "link_komisi": "https://s.shopee.co.id/7fUvKJwE3s"
  },
  {
    "nama_produk": "CELANA JEANS PANJANG PRIA SOBEK EMBLEM BORDIL KEREN PREMIUM DISTRO ORIGINAL",
    "harga": "71,2RB",
    "link_komisi": "https://s.shopee.co.id/7VBVevs7re"
  },
  {
    "nama_produk": "Jersey Anak Vintage Jersey MiniMovers Number Series Bahan Dryfit Brazil Jersey Unisex",
    "harga": "31,0RB",
    "link_komisi": "https://s.shopee.co.id/7Ks5ScslCd"
  },
  {
    "nama_produk": "ABAYA HAWA 735 FARZOLLA - Busana Muslim Wanita",
    "harga": "230,0RB",
    "link_komisi": "https://s.shopee.co.id/7AYfGJtOXc"
  },
  {
    "nama_produk": "Mixer elektrik 3 kecepatan yang dapat diatur, mixer tangan tanpa kabel, mixer adonan kue elektrik [BISA COD]",
    "harga": "35,0RB",
    "link_komisi": "https://s.shopee.co.id/70FF40u1sb"
  },
  {
    "nama_produk": "Samsung Galaxy A56 5G 12/256GB - Awesome Graphite | Galaxy AI | 50MP Camera | 45W Super Fast Charge",
    "harga": "6,8JT",
    "link_komisi": "https://s.shopee.co.id/6pvorhufDa"
  },
  {
    "nama_produk": "KF CAT Setelan Anak Perempuan Gaya Korea 2in1 - Atasan Katun Beludru + Celana Panjang Usia 1-5thn",
    "harga": "85,0RB",
    "link_komisi": "https://s.shopee.co.id/6fcOfOvIYZ"
  },
  {
    "nama_produk": "Agatha Outer Lace Mix Ceruty Babydoll",
    "harga": "120,0RB",
    "link_komisi": "https://s.shopee.co.id/3fyn5t6ie0"
  },
  {
    "nama_produk": "Clara Jaket Jeans denim Crop Wanita Retro Vintage Oversize",
    "harga": "91,2RB",
    "link_komisi": "https://s.shopee.co.id/3qIDIC65J3"
  },
  {
    "nama_produk": "Promo Daster Resleting Termurah / Daster Jumbo Wolfis Poli Katun Sanwos Terlaris",
    "harga": "19,5RB",
    "link_komisi": "https://s.shopee.co.id/3LLwhH7zJy"
  },
  {
    "nama_produk": "H76 Sepatu Sandal Wanita Baim Sendal jibbitz Sandal DIY Sepatu Wedges sandal kodok Sandal Slop Wanita Kekinian Sandal Kodok Wanita Sandal Fuji Sandal Baim Tali Pengikat Wedges Anti-selip",
    "harga": "35,8RB",
    "link_komisi": "https://s.shopee.co.id/3VfMta7Lz1"
  },
  {
    "nama_produk": "gamis anjani rayon premium - gamis pita anjani - gamis rayon premium motif kekinian",
    "harga": "87,9RB",
    "link_komisi": "https://s.shopee.co.id/30j6If9Fzw"
  },
  {
    "nama_produk": "Terlaris [PAKET BUNDLING] Seblak Mix/Campur & Seblak Kerupuk jengkol pedas daun jeruk",
    "harga": "22,0RB",
    "link_komisi": "https://s.shopee.co.id/3B2WUy8cez"
  },
  {
    "nama_produk": "BAJU KOKO TANGAN PANJANG JASCO EXCLUSIV KAFANA Baju Muslim Pria Modern",
    "harga": "97,0RB",
    "link_komisi": "https://s.shopee.co.id/2g6Fu3AWfu"
  },
  {
    "nama_produk": "ASP_Tas Bahu Wanita Shoulder Bag Berbahan Kulit Sintetis",
    "harga": "10,6RB",
    "link_komisi": "https://s.shopee.co.id/2qPg6M9tKx"
  },
  {
    "nama_produk": "Sajadah Turki Emboss Polos Motif Kubah Terlaris Warna Random",
    "harga": "52,0RB",
    "link_komisi": "https://s.shopee.co.id/50UAgL1dwO"
  },
  {
    "nama_produk": "Wafer Cokelat Roll 1 Karton isi 6 Rakyat Ketjil",
    "harga": "79,0RB",
    "link_komisi": "https://s.shopee.co.id/5Anase10bR"
  },
  {
    "nama_produk": "Mukena Anak Perempuan 1-8 tahun Peralatan Sholat Fashion Muslim terlaris selama",
    "harga": "34,0RB",
    "link_komisi": "https://s.shopee.co.id/4frKHj2ucM"
  },
  {
    "nama_produk": "Boneka Loopy Imut - Gantungan Tas & Kunci Squishy, Mainan Anti Stress untuk Cewek",
    "harga": "9,8RB",
    "link_komisi": "https://s.shopee.co.id/4qAkU22HHP"
  },
  {
    "nama_produk": "Sajadah Tebal Premium Kubah Motif Anti Slip Turki Ukuran Standar Besar Nyaman & Lembut ( 70x110cm )",
    "harga": "59,0RB",
    "link_komisi": "https://s.shopee.co.id/4LETt74BIK"
  },
  {
    "nama_produk": "Baju Muslim Pria Kemeja koko Sultan Embos Ethnic Lengan Panjang",
    "harga": "143,4RB",
    "link_komisi": "https://s.shopee.co.id/4VXu5Q3XxN"
  },
  {
    "nama_produk": "Glad2Glow Renew bundle 7in1 7pcs-Brightening toner+Brightening Moisturizer+Milk Cleanser+Brightenin...",
    "harga": "125,0RB",
    "link_komisi": "https://s.shopee.co.id/40bdUV5RyI"
  },
  {
    "nama_produk": "Glad2Glow Peach Retinol Moisturizer 30g Untuk Kulit Berjerawat",
    "harga": "35,5RB",
    "link_komisi": "https://s.shopee.co.id/4Av3go4odL"
  },
  {
    "nama_produk": "Kasur Ignite Haven Premium Moccaholic Edition Tebal Nyaman Anti Kempes | Garansi 15 Tahun",
    "harga": "281,7RB",
    "link_komisi": "https://s.shopee.co.id/10y1uzGs3k"
  },
  {
    "nama_produk": "NIGOS Ar-Rafi Dewasa Kemeja Koko Baju muslim pria Baju koko pria dewasa lengan pendek bahan katun ok",
    "harga": "155,8RB",
    "link_komisi": "https://s.shopee.co.id/1BHS7IGEin"
  },
  {
    "nama_produk": "Mukena Dewasa Gracella Exclusive Bunga Teratai Full Bordir Katun Premium",
    "harga": "80,0RB",
    "link_komisi": "https://s.shopee.co.id/gLBWNI8ji"
  },
  {
    "nama_produk": "PROMO 10 BUNGKUS KUE KACANG NASTAR KASTANGEL RANDOM KEMASAN SERBA ISI 1 PCS",
    "harga": "15,0RB",
    "link_komisi": "https://s.shopee.co.id/qebigHVOl"
  },
  {
    "nama_produk": "Baju Koko Palestina Anak Motif Model Terbaru 2023 Baju Muslim Taqwa Anak Cowok El-Rumi Alisan Premium",
    "harga": "52,7RB",
    "link_komisi": "https://s.shopee.co.id/LiL7lJPPg"
  },
  {
    "nama_produk": "Parfum Aura GENTLEMAN RULES Original Extrait De Parfum 2 Days by Yayang Sundawa, Parfum Pria,Cowok Premium",
    "harga": "119,1RB",
    "link_komisi": "https://s.shopee.co.id/W1lK4Im4j"
  },
  {
    "nama_produk": "[ FMLY ] Mireya Blouse Kerut Dada Lengan Panjang Bahan Rayon Atasan Wanita Terbaru",
    "harga": "130,0RB",
    "link_komisi": "https://s.shopee.co.id/15Uj9Kg5e"
  },
  {
    "nama_produk": "Rockmaker Celana Denim Slim Fit Selvedge Accent Barley",
    "harga": "174,9RB",
    "link_komisi": "https://s.shopee.co.id/BOuvSK2kh"
  },
  {
    "nama_produk": "Apple IPHONE 12 /64GB/128GB ORIGINAL MULUS GOOD CONDITIONS FULLSET MULUS SECOND 100%",
    "harga": "3,2JT",
    "link_komisi": "https://s.shopee.co.id/2LTPVRBnM8"
  },
  {
    "nama_produk": "[20ML ONLY FREE 5ML] Decant Velixir Parfums All Variant | Premium Original 100 %",
    "harga": "85,8RB",
    "link_komisi": "https://s.shopee.co.id/2VmphkBA1B"
  },
  {
    "nama_produk": "Cermin Bunga Standing Mirror Berotasi 360 Makeup Rotating Cermin Aesthetic - Stand Mirorr Flower Kaca Meja Rias Serbaguna",
    "harga": "8,0RB",
    "link_komisi": "https://s.shopee.co.id/20qZ6pD426"
  },
  {
    "nama_produk": "[COD] Parfum laundry murah - wanginya tahan lama - pelicin dan pengharum baju anti apek anti jamur",
    "harga": "18,4RB",
    "link_komisi": "https://s.shopee.co.id/2B9zJ8CQh9"
  },
  {
    "nama_produk": "Valir FGT Jaket Bomber Pria Keren Kekinian Terbaru Jacket Pria Outdoor Jaket Anti Air Waterproof",
    "harga": "189,0RB",
    "link_komisi": "https://s.shopee.co.id/1gDiiDEKi4"
  },
  {
    "nama_produk": "QUIRINO - Cardigan rajutan pendek wanita kancing leher bulat ala Korea Sweater cardigan rajutan pendek yang lucu",
    "harga": "99,0RB",
    "link_komisi": "https://s.shopee.co.id/1qX8uWDhN7"
  },
  {
    "nama_produk": "COD Jeans Celana Jeans terbaru kulot Korea Biru muda pinggang tinggi--Baggy Jeans -baggy baggy",
    "harga": "87,7RB",
    "link_komisi": "https://s.shopee.co.id/1LasJbFbO2"
  },
  {
    "nama_produk": "Kaos Katun Tahan Lama, Bahan Kuat, Hemat Beli Berulang",
    "harga": "45,0RB",
    "link_komisi": "https://s.shopee.co.id/1VuIVuEy35"
  },
  {
    "nama_produk": "OPTIVIA Toples Aklirik kedap udara gold emas / Toples set 3pcs/set mewah / Toples mewah aesthetic Toples Snack emas /Toples Dubai Kedap Udara /Toples Kue Lebaran Mewah",
    "harga": "115,0RB",
    "link_komisi": "https://s.shopee.co.id/900JRgmPpY"
  },
  {
    "nama_produk": "ANGOLA Lemari Pakaian Anak 4 5 Tingkat C70-C71 Tempat Penyimpanan Mainan/Snack/Baju Serbaguna",
    "harga": "66,0RB",
    "link_komisi": "https://s.shopee.co.id/9AJj72SIdg"
  },
  {
    "nama_produk": "Libasulafiyah Baju Kemko Kombinasi Kemeja Koko Pria Dewasa Shanghai Lengan Panjang Bahan Katun Madinah Songket - Baju Muslim Pria dewasa kemko kemeja koko Fashion Terbaru Terlaris 2026",
    "harga": "93,5RB",
    "link_komisi": "https://s.shopee.co.id/8fNT34ngVW"
  },
  {
    "nama_produk": "[ COD PABRIK ] Jopperside baju kaos polos kancing henley katun combed premium pria tb2",
    "harga": "46,0RB",
    "link_komisi": "https://s.shopee.co.id/8pgtFNn3AZ"
  },
  {
    "nama_produk": "(SET5IN1) Kebaya Kutubaru Nadya Modern Aesthetic Set Kebaya Wisuda Baju Kondangan Wanita Kekinian",
    "harga": "110,7RB",
    "link_komisi": "https://s.shopee.co.id/8KkceSoxBU"
  },
  {
    "nama_produk": "BRAVHOM Kipas Angin Mini Portable 3IN1 Powerbank 3600mAh Aromaterapi Kipas Angin Portable BL-FN16",
    "harga": "33,2RB",
    "link_komisi": "https://s.shopee.co.id/8V42qloJqX"
  },
  {
    "nama_produk": "[ share in jar ] instan tone up body serum lavojoy",
    "harga": "14,9RB",
    "link_komisi": "https://s.shopee.co.id/807mFqqDrS"
  },
  {
    "nama_produk": "KIMURA CARNU - Tas Wanita -Tas Selempang -Tas Import -Slingbag Rajut #6120",
    "harga": "98,0RB",
    "link_komisi": "https://s.shopee.co.id/1BIIt2YaJd"
  },
  {
    "nama_produk": "( isi 2 pcs ) jaket couple B Signature pasangan / jaket pasangan pacar / jaket couple sahabat",
    "harga": "124,2RB",
    "link_komisi": "https://s.shopee.co.id/gM2I7aUKY"
  },
  {
    "nama_produk": "ZORA Aksesoris Fashion Jewelry Kalung Rantai O Manik-Manik Kupu-Kupu Wanita Bekarat Kalung Titanium Anti Karat Lapis Emas Necklaces X004",
    "harga": "18,5RB",
    "link_komisi": "https://s.shopee.co.id/qfSUQZqzb"
  },
  {
    "nama_produk": "Mosswood Springbed Hotel Premium 20cm Kasur Busa Pegas Anti Goyang Tahan Lama Bonus Bantal Gratis Ongkir",
    "harga": "899,0RB",
    "link_komisi": "https://s.shopee.co.id/LjBtVbl0W"
  },
  {
    "nama_produk": "Adiba | Mukena Dewasa Katun Foil Premium Motif Terbaru 2in1",
    "harga": "125,0RB",
    "link_komisi": "https://s.shopee.co.id/W2c5ob7fZ"
  },
  {
    "nama_produk": "PUMA Shuffle Sneakers",
    "harga": "799,0RB",
    "link_komisi": "https://s.shopee.co.id/16LUtd1gU"
  },
  {
    "nama_produk": "ZRBR - Tas Selempang Wanita Import Kekinian Terbaru Tas Pesta Hangout Sling Bag Elegant - Chico Sling Bag #9030",
    "harga": "148,0RB",
    "link_komisi": "https://s.shopee.co.id/BPlhCcOLX"
  },
  {
    "nama_produk": "Kasur Ignite Haven Premium Moccaholic Edition Tebal Nyaman Anti Kempes | Garansi 15 Tahun",
    "harga": "360,9RB",
    "link_komisi": "https://s.shopee.co.id/2LUGHBU8wy"
  },
  {
    "nama_produk": "[CID] Powerbank 20000 mAh Mini With 4 USB Cable Fast Charging Lightweight Universal Powerbank LED Display",
    "harga": "63,8RB",
    "link_komisi": "https://s.shopee.co.id/2VngTUTVc1"
  },
  {
    "nama_produk": "ZARA WOMEN ORCHID  / PARFUME WANITA TERLARIS",
    "harga": "9,2RB",
    "link_komisi": "https://s.shopee.co.id/20rPsZVPcw"
  },
  {
    "nama_produk": "RAYYA BAG Tas Selempang wanita 2023 Tas Hp Wanita Slingbag Mini wanita Tas Selempang Mini Wanita Kekinian Tas wanita Selempang Hp wanita kekinian Slingbag wanita Tas Hp wanita Tas Selempang Hp wanita Tas Selempang wanita Import",
    "harga": "26,5RB",
    "link_komisi": "https://s.shopee.co.id/2BAq4sUmHz"
  },
  {
    "nama_produk": "Emeron Lovely Naturals Hand & Body Lotion Whitening Pump 400ml (PUMP)",
    "harga": "10,7RB",
    "link_komisi": "https://s.shopee.co.id/1gEZTxWgIu"
  },
  {
    "nama_produk": "Gamis Batik Couple Suami Istri Modern Size Standar dan Jumbo,",
    "harga": "179,0RB",
    "link_komisi": "https://s.shopee.co.id/1qXzgGW2xx"
  },
  {
    "nama_produk": "PARFUM AROMA PERMEN KARET 30ML BOTOL KOTAK, PARFUM BUBLE GUM TERLARIS",
    "harga": "9,2RB",
    "link_komisi": "https://s.shopee.co.id/1Lbj5LXwys"
  },
  {
    "nama_produk": "Tas Wanita Bordir Kontak Kontak Free Gantungan Boneka Selempang Perempuan Tas Tangan cewek",
    "harga": "35,1RB",
    "link_komisi": "https://s.shopee.co.id/1Vv9HeXJdv"
  },
  {
    "nama_produk": "VISHAL Combo 3IN1 (COD) Stainless Blender Daging Penggiling +1Set Pisau + 4Pcs Mangkuk Set",
    "harga": "119,0RB",
    "link_komisi": "https://s.shopee.co.id/3fzdrdP4FM"
  },
  {
    "nama_produk": "retro mini pouch ready stock",
    "harga": "119,0RB",
    "link_komisi": "https://s.shopee.co.id/3qJ43wOQuP"
  },
  {
    "nama_produk": "TRENDING BELI 1 DAPAT 2 PARFUM VANILLA | Parfum wanita tahan lama 24 jam - Parfum cewek Terlaris - Parfum Viral - 35ml Eau De Parfume",
    "harga": "9,3RB",
    "link_komisi": "https://s.shopee.co.id/3LMnT1QKvK"
  },
  {
    "nama_produk": "Tas Selempang Kulit Wanita Tas Cewek Mini Handbag Shoulder Bag/Tas Selempang Wanita tas wanita tas bahu wanita Tas Impor",
    "harga": "60,1RB",
    "link_komisi": "https://s.shopee.co.id/3VgDfKPhaN"
  },
  {
    "nama_produk": "VISHAL Blender Portable mini Kapsul cutter Quatre/BLENDER KAPSUL SERBAGUNA VS-1828",
    "harga": "69,0RB",
    "link_komisi": "https://s.shopee.co.id/30jx4PRbbI"
  },
  {
    "nama_produk": "[COD] Kalung Liontin Titanium Semanggi Wanita Korea Anti Karat Mewah Clover Kalung Gaya Wangi Kecil SY",
    "harga": "9,4RB",
    "link_komisi": "https://s.shopee.co.id/3B3NGiQyGL"
  },
  {
    "nama_produk": "Lipstik Matte ZENCOLOR Urban Original 20 Varian Warna - Lip Cream Matte Moisturizer Liquid",
    "harga": "13,5RB",
    "link_komisi": "https://s.shopee.co.id/2g76fnSsHG"
  },
  {
    "nama_produk": "Rak Serbaguna Plastik Rak Susun Rak Komestik Rak Penyimpanan 3 & 4 Tingkat",
    "harga": "45,0RB",
    "link_komisi": "https://s.shopee.co.id/2qQWs6SEwJ"
  },
  {
    "nama_produk": "VOOVA Sandal Selop Wanita/ Sandal Indoor/Sandal Wanita Karet/Sandal Rumah/Sandal Luar Rumah",
    "harga": "25,9RB",
    "link_komisi": "https://s.shopee.co.id/50V1S5JzXk"
  },
  {
    "nama_produk": "Novilla kasur IceMint spons busa springbed tebal 25/30cm empuk lantai matras anti lembab Free bantal",
    "harga": "1,2JT",
    "link_komisi": "https://s.shopee.co.id/5AoReOJMCn"
  },
  {
    "nama_produk": "FLICKA Abby Bag Shoulder Bag Tas Bahu Selempang Wanita Terbaru",
    "harga": "109,0RB",
    "link_komisi": "https://s.shopee.co.id/4fsB3TLGDi"
  },
  {
    "nama_produk": "HUGO Rak Dapur Serbaguna Rak Troli Rak Kamar Mandi Rak Susun Plastik dengan Roda",
    "harga": "55,0RB",
    "link_komisi": "https://s.shopee.co.id/4qBbFmKcsl"
  },
  {
    "nama_produk": "Philips Rice Cooker Magicom 1.8 L - 3000 Premium Series HD3211/32 - Gold - Bakuhanseki Inner Pot - Anti lengket - FreshDefense Technology - Nasi No Basi hingga 48 Jam - 400 Watt",
    "harga": "709,0RB",
    "link_komisi": "https://s.shopee.co.id/4LFKerMWtg"
  },
  {
    "nama_produk": "Selimut Bulu Dewasa Halus 150x200 Motif Paling Keren Terlaris Termurah Asriyasashii Berkualitas",
    "harga": "39,5RB",
    "link_komisi": "https://s.shopee.co.id/4VYkrALtYj"
  },
  {
    "nama_produk": "[In-stock] Glad2Glow BRIGHTENING LIP SERUM 7g  Mencerahkan Melembabkan dan menambahkan warna3in1  liptint lipstick lipcream &Metal Applicatior cooling sensation Tahan Lama dan Vitamin E danVitamin C Cushion  g2glow official store",
    "harga": "56,9RB",
    "link_komisi": "https://s.shopee.co.id/40cUGFNnZe"
  },
  {
    "nama_produk": "Rak troli plastik rak toilet rak kamar mandi rak dapur serbaguna dengan roda Rak Bumbu Rak Susun Kosmetik",
    "harga": "28,0RB",
    "link_komisi": "https://s.shopee.co.id/4AvuSYNAEh"
  },
  {
    "nama_produk": "Samsung Kulkas 2 Pintu 203L | Anti|Bacterial | Hemat Energi | All Around Cooling | RT19M300BGS/SE",
    "harga": "3,8JT",
    "link_komisi": "https://s.shopee.co.id/6L0P2XEuq8"
  },
  {
    "nama_produk": "Kasur Busa Roll Extra Empuk Kain Knitting Quilting Premium / Kasur Tidur Empuk Tahan Hingga 100KG Super Awet / Matras Matress Roll Tebal 10/15 CM [GARANSI RESMI]",
    "harga": "327,6RB",
    "link_komisi": "https://s.shopee.co.id/6VJpEqEHVB"
  },
  {
    "nama_produk": "TAS SHOULDER BAG WANITA - SHOULDERBAG WANITA KEKINIAN - TAS BAHU WANITA - TAS KONDANGAN WANITA TERBARU",
    "harga": "17,8RB",
    "link_komisi": "https://s.shopee.co.id/60NYdvGBW6"
  },
  {
    "nama_produk": "BOBEINI Mascara Length Steel Maskara Waterproof Sweatproof Smudgeproof Panjang Lentik - LA017 772",
    "harga": "5,8RB",
    "link_komisi": "https://s.shopee.co.id/6AgyqEFYB9"
  },
  {
    "nama_produk": "DOMPET CROCO KANCING",
    "harga": "10,5RB",
    "link_komisi": "https://s.shopee.co.id/5fkiFJHSC4"
  },
  {
    "nama_produk": "Fortisse Mattress Busa Anti-noda High Density Foam - Garansi 15 Tahun High Quality",
    "harga": "448,4RB",
    "link_komisi": "https://s.shopee.co.id/5q48RcGor7"
  },
  {
    "nama_produk": "ANGOLA Lemari Pakaian Anak 4 5 Tingkat C70-C71 Tempat Penyimpanan Mainan/Snack/Baju Serbaguna",
    "harga": "66,9RB",
    "link_komisi": "https://s.shopee.co.id/5L7rqhIis2"
  },
  {
    "nama_produk": "ALVA - ALVA N3 NEXT GEN Sepeda Motor Listrik Berlangganan Baterai Sewa",
    "harga": "15,5JT",
    "link_komisi": "https://s.shopee.co.id/5VRI30I5X5"
  },
  {
    "nama_produk": "SANDAL KOKOP WANITA MOTIF BEAR | SENDAL KOKOP TERBARU DEWASA MOTIF EMBOS UNIK SELOP",
    "harga": "9,7RB",
    "link_komisi": "https://s.shopee.co.id/7fVmcz9q8W"
  },
  {
    "nama_produk": "Rak Dapur Makanan Tabita food Grade, Penyimpanan Praktis dan Aman Multifungsi Food Cabinet Tabitha",
    "harga": "105,0RB",
    "link_komisi": "https://s.shopee.co.id/7ppCpI9CnZ"
  },
  {
    "nama_produk": "jilbab sport pet tebal / bergo sport pet tebal / jilbab instan / hijab bergo pet tebal",
    "harga": "18,0RB",
    "link_komisi": "https://s.shopee.co.id/7KswENB6oU"
  },
  {
    "nama_produk": "Rak troli plastik rak toilet rak kamar mandi rak dapur serbaguna dengan roda Rak Bumbu Rak Susun Kosmetik",
    "harga": "26,9RB",
    "link_komisi": "https://s.shopee.co.id/7VCMQgATTX"
  },
  {
    "nama_produk": "Sandal Jepit Wanita Anti Slip Berkualita/Sandal Wanita",
    "harga": "15,0RB",
    "link_komisi": "https://s.shopee.co.id/70G5plCNUS"
  },
  {
    "nama_produk": "Tas Selempang Wanita Kekinian Terbaru Shoulder Bag Sling Bag Hand Bag Korea Style",
    "harga": "11,9RB",
    "link_komisi": "https://s.shopee.co.id/7AZW24Bk9V"
  },
  {
    "nama_produk": "Promo Celana Cutbray Wanita Basic Bahan Scuba Premium Fit & Flare Celana Kerja Highwaist Jumbo Melar",
    "harga": "26,9RB",
    "link_komisi": "https://s.shopee.co.id/6fdFR9DeAQ"
  },
  {
    "nama_produk": "ASP Ayra Tas Wanita Korea Sintetis Kerut 31x21x8cm",
    "harga": "12,0RB",
    "link_komisi": "https://s.shopee.co.id/6pwfdSD0pT"
  },
  {
    "nama_produk": "Coolrain Sandal Baim Wanita Kasual Sendal kodok Anti Selip Sandal Classic Eva Dan Karet Sandal Terbaru HSN105(Size 30-43)",
    "harga": "34,9RB",
    "link_komisi": "https://s.shopee.co.id/901ADR4lQu"
  },
  {
    "nama_produk": "ASP_Tas Bahu Wanita Shoulder Bag Berbahan Kulit Sintetis",
    "harga": "13,3RB",
    "link_komisi": "https://s.shopee.co.id/9AKaPk485x"
  },
  {
    "nama_produk": "Jam Tangan Wanita Murah Fashion Casual Quartz Analog Women Leather Watch",
    "harga": "17,6RB",
    "link_komisi": "https://s.shopee.co.id/8fOJop626s"
  },
  {
    "nama_produk": "Evangeline Selection Eau De Parfum Green Tea 100ml | Parfum Wanita EDP Tahan Lama",
    "harga": "38,6RB",
    "link_komisi": "https://s.shopee.co.id/8phk185Olv"
  },
  {
    "nama_produk": "Attack Plus Softener Deterjen Cair Semua Mesin Cuci 1200mL Triple Pack",
    "harga": "104,7RB",
    "link_komisi": "https://s.shopee.co.id/8KlTQD7Imq"
  },
  {
    "nama_produk": "Gamis outer abaya mewah gamis lebaran terbaru 2025",
    "harga": "54,9RB",
    "link_komisi": "https://s.shopee.co.id/8V4tcW6fRt"
  },
  {
    "nama_produk": "cover sarung mobil avanza xenia calya sigra ertiga jazz agya ayla tali ban",
    "harga": "185,0RB",
    "link_komisi": "https://s.shopee.co.id/808d1b8ZSo"
  },
  {
    "nama_produk": "❤ BELIA ❤ WARDAH Colorfit Velvet Matte Lip Mousse | Lipstik cair dengan tekstur mousse 4 gram",
    "harga": "64,8RB",
    "link_komisi": "https://s.shopee.co.id/8AS3Du7w7r"
  },
  {
    "nama_produk": "HIT Expert Raket Nyamuk - Raket Nyamuk - Bunuh Nyamuk Penyebab Demam Berdarah (DBD)",
    "harga": "135,3RB",
    "link_komisi": "https://s.shopee.co.id/AKWXnszgjI"
  },
  {
    "nama_produk": "PASHMINA CRINKLE / PASHMINA KUSUT RAWIS Mei Chen PASHMINA CRINKLE Premium Shawl ORI hijab[YUEXIU2]",
    "harga": "14,9RB",
    "link_komisi": "https://s.shopee.co.id/AUpy0Bz3OL"
  },
  {
    "nama_produk": "Fleco Super X-Bass Speaker karaoke Bluetooth fleco Super Bass",
    "harga": "270,3RB",
    "link_komisi": "https://s.shopee.co.id/9zthPH0xPG"
  },
  {
    "nama_produk": "[CID] Kipas Angin Mini Portable USB Genggam N68 Layar LED Angin Kencang 100 High Speed Handheld Fan Adjustable Fan Speed Digital Display",
    "harga": "35,8RB",
    "link_komisi": "https://s.shopee.co.id/AAD7ba0K4J"
  },
  {
    "nama_produk": "SANDAL BAIM HAK TINGGI SANDAL KODOK SANDAL BAPAO CEWE COWO SANDAL PERAWAT SANDAL COUPLE BAIM",
    "harga": "36,5RB",
    "link_komisi": "https://s.shopee.co.id/9fGr0f2E5E"
  },
  {
    "nama_produk": "MANGKOK TULIP 12 PCS (1 LUSIN) BANYAK VARIAN",
    "harga": "14,0RB",
    "link_komisi": "https://s.shopee.co.id/9paHCy1akH"
  },
  {
    "nama_produk": "Goovin - Work Shirt  - Boxy Fit - Flow",
    "harga": "275,0RB",
    "link_komisi": "https://s.shopee.co.id/9Ke0c33UlC"
  },
  {
    "nama_produk": "Tas Wanita Shoulder Bag Wanita Vintage Laila Bag Korea Kekinian Terbaru Tas bahu Bag",
    "harga": "37,9RB",
    "link_komisi": "https://s.shopee.co.id/9UxQoM2rQF"
  },
  {
    "nama_produk": "Amicaa - Sweatpants Loose Highwaist Celana Panjang Daily Wanita Nyaman Soft Lembut Tebal",
    "harga": "54,9RB",
    "link_komisi": "https://s.shopee.co.id/1BIIt2YaKe"
  },
  {
    "nama_produk": "ACC 2127 FREM LENTUR LENSA NORMAL MINUS PHOTOCROMIC BLUCROMIC FASHIOM WANITA PRIA LENSA OPTICK FREE BOX DAN LAP MURAH BERKUALITAS",
    "harga": "99,0RB",
    "link_komisi": "https://s.shopee.co.id/10ysgjZDfd"
  },
  {
    "nama_produk": "No Void Minds FORMLOCK Oversized T-Shirt | Steel",
    "harga": "99,9RB",
    "link_komisi": "https://s.shopee.co.id/qfSUQZr0c"
  },
  {
    "nama_produk": "sandal ANDIN JEPIT TERBARU",
    "harga": "12,0RB",
    "link_komisi": "https://s.shopee.co.id/gM2I7aULb"
  },
  {
    "nama_produk": "TEMPLATE DASHBOARD KEUANGAN Pribadi/Keluarga, Mencatat Pendapatan Pengeluaran Aset & Laporan. Interaktif",
    "harga": "27,0RB",
    "link_komisi": "https://s.shopee.co.id/W2c5ob7ga"
  },
  {
    "nama_produk": "Kacamata Minus -1 -2 -3 -4 -5 -6 Fashion Korea Anti Blue Light Anti Radiasi Smartphone Dan Laptop Model Cat Eye",
    "harga": "21,9RB",
    "link_komisi": "https://s.shopee.co.id/LjBtVbl1Z"
  },
  {
    "nama_produk": "Masker Duckbill Isi 50pcs 3Ply Facemask Earloop Disposable",
    "harga": "9,3RB",
    "link_komisi": "https://s.shopee.co.id/BPlhCcOMY"
  },
  {
    "nama_produk": "【Buy 1 Get 1】Tas Bahu Wanita Shoulder Bag Mini Simple Style Fashion Tali Adjust Tas Wanita Import#200",
    "harga": "78,0RB",
    "link_komisi": "https://s.shopee.co.id/16LUtd1hX"
  },
  {
    "nama_produk": "Celana Panjang Wanita Loose High Waist Jeans Premium - Korean Stayle Jeans Baggy Loose Oversize",
    "harga": "60,0RB",
    "link_komisi": "https://s.shopee.co.id/2VngTUTVd2"
  },
  {
    "nama_produk": "No Void Minds AEZY Regular T-Shirt | Charcoal",
    "harga": "61,9RB",
    "link_komisi": "https://s.shopee.co.id/2LUGHBU8y1"
  },
  {
    "nama_produk": "[TWINPACK] SENKA Perfect Whip Vibrant White Facial Foam From Japan 100gr [BUY 2 GET 4 Hadiah Terbatas/Hari]",
    "harga": "131,0RB",
    "link_komisi": "https://s.shopee.co.id/2BAq4sUmJ0"
  },
  {
    "nama_produk": "MKMC Tas selempang Wanita Import Moon Bag Zipper Embos Shoulder Bag Kulit Kekinian Make Up Resleting Multifungsi Fashion Crossbody Bag Kondangan Tas Bahu Slingbag Polos Casual Terbaru Korean Style Terbaru COD",
    "harga": "119,0RB",
    "link_komisi": "https://s.shopee.co.id/20rPsZVPdz"
  },
  {
    "nama_produk": "KENAN - Pashmina Airflow Rayon basic scarf Cooltech",
    "harga": "62,0RB",
    "link_komisi": "https://s.shopee.co.id/1qXzgGW2yy"
  },
  {
    "nama_produk": "6504 958 Eyebrow Cream Waterproof & Long Lasting Free Kuas",
    "harga": "7,5RB",
    "link_komisi": "https://s.shopee.co.id/1gEZTxWgJx"
  },
  {
    "nama_produk": "Baju Muslim Pria Jubah Gamis Altan ORIGINAL RAFVERO",
    "harga": "103,7RB",
    "link_komisi": "https://s.shopee.co.id/1Vv9HeXJew"
  },
  {
    "nama_produk": "TAS SLEMPANG FREYA PREMIER/TAS MINI/TAS TERLARIS/TAS UKURAN KECIL",
    "harga": "13,9RB",
    "link_komisi": "https://s.shopee.co.id/1Lbj5LXwzv"
  },
  {
    "nama_produk": "WORKSHEET ANAK BUKU AKTIFITAS ANAK PAUD/TK",
    "harga": "28,5RB",
    "link_komisi": "https://s.shopee.co.id/3qJ43wOQvQ"
  },
  {
    "nama_produk": "OMG - OMBRE BUNDLE LIP SERIES - Lip Tint | Lip Cream | Warna Intense, Tahan Lama & Ringan",
    "harga": "41,6RB",
    "link_komisi": "https://s.shopee.co.id/3fzdrdP4GP"
  },
  {
    "nama_produk": "JISJIA Kipas 100 Gear Mini LED Kipas Turbo Angin Strong Wind Wind Angin Tampilan Digital Kipas",
    "harga": "80,0RB",
    "link_komisi": "https://s.shopee.co.id/3VgDfKPhbO"
  },
  {
    "nama_produk": "Oro Pants Stripe Salur - Celana Panjang Korean Style - Celana Highwaist - Celana Anti Kusut",
    "harga": "42,1RB",
    "link_komisi": "https://s.shopee.co.id/3LMnT1QKwN"
  },
  {
    "nama_produk": "Bitzen Ikat Pinggang Wanita Kulit Sapi Slim Casual Belt Wanita Dengan Gesper Sabuk Pinggang Wanita Tali Pinggang Wanita",
    "harga": "52,6RB",
    "link_komisi": "https://s.shopee.co.id/3B3NGiQyHM"
  },
  {
    "nama_produk": "Parfum Kualitas Premium Vanilla Cake Paling Wangi EDP 35ML",
    "harga": "6,9RB",
    "link_komisi": "https://s.shopee.co.id/30jx4PRbcL"
  },
  {
    "nama_produk": "BRAVHOM Pompa Galon Elektrik Dapat Dilipat Desinfektan SinarUv Dispenser Air Galon Portable BL-WD02",
    "harga": "54,0RB",
    "link_komisi": "https://s.shopee.co.id/2qQWs6SExK"
  },
  {
    "nama_produk": "Tumbler Jepang/Botol Minum Macaroon Kaca 500mL Bonus Gantungan Boneka Labubu Botol Minum Cantik Viral Lucu Terbaru Tumbler Aesthetic",
    "harga": "23,6RB",
    "link_komisi": "https://s.shopee.co.id/2g76fnSsIJ"
  },
  {
    "nama_produk": "[SPECIAL PRICE] HONYAN Tas Shoulder Bag Tas Wanita Original Tas Bahu Wanita - Kimi Vintage Shoulder Bag",
    "harga": "99,9RB",
    "link_komisi": "https://s.shopee.co.id/5AoReOJMDo"
  },
  {
    "nama_produk": "ANQI SHOP TIKAR Piknik TEBAL WATERPROOF Alas Piknik Tikar Piknik Outdoor 1 x 1,5 m VS-32",
    "harga": "40,0RB",
    "link_komisi": "https://s.shopee.co.id/50V1S5JzYn"
  },
  {
    "nama_produk": "ANQI SHOP Chopper Blender daging penggiling Meat Blender Elektrik Stainless Steel Chopper Grinder/VS",
    "harga": "90,0RB",
    "link_komisi": "https://s.shopee.co.id/4qBbFmKctm"
  },
  {
    "nama_produk": "HAPPY Daffi Hijab Instan Bergo Jilbab Best Seller Pad Antem Aksen Mini Logo emas Terbaru",
    "harga": "77,0RB",
    "link_komisi": "https://s.shopee.co.id/4fsB3TLGEl"
  },
  {
    "nama_produk": "MOSSDOOM Tas Selempang Wanita Darby Bag Tas Sling Bag Wanita Tas Bahu",
    "harga": "144,9RB",
    "link_komisi": "https://s.shopee.co.id/4VYkrALtZk"
  },
  {
    "nama_produk": "JOOBSD Workshrit 'Ambra' - Workshirt Zipper - Hitam - Unisex",
    "harga": "100,0RB",
    "link_komisi": "https://s.shopee.co.id/4LFKerMWuj"
  },
  {
    "nama_produk": "Panci Listrik Serbaguna Hemat Listrik 450W / Elektrik Cooker Multifunsi / Panci listrik Anti Lengket hemat Listrik",
    "harga": "54,5RB",
    "link_komisi": "https://s.shopee.co.id/4AvuSYNAFi"
  },
  {
    "nama_produk": "Kemeja Wanita Ribonia Salur Katun Pita Bordir",
    "harga": "38,0RB",
    "link_komisi": "https://s.shopee.co.id/40cUGFNnah"
  },
  {
    "nama_produk": "Rak Dapur 4 Susun Rak Troli Serbaguna Rak Persegi Rak Segitiga",
    "harga": "24,9RB",
    "link_komisi": "https://s.shopee.co.id/6VJpEqEHWC"
  },
  {
    "nama_produk": "Basreng Pedas Daun Jeruk/ Original / Balado 100 Gram",
    "harga": "6,0RB",
    "link_komisi": "https://s.shopee.co.id/6L0P2XEurB"
  },
  {
    "nama_produk": "(KM51) Kacamata Gagang Lentur Kacamata Anti Radiasi Kacamata Fashion",
    "harga": "14,5RB",
    "link_komisi": "https://s.shopee.co.id/6AgyqEFYCA"
  },
  {
    "nama_produk": "Biore Body Foam Sabun Mandi Cair Relaxing Aromatic Pump 550ml \n",
    "harga": "52,0RB",
    "link_komisi": "https://s.shopee.co.id/60NYdvGBX9"
  },
  {
    "nama_produk": "Blender Kapsul Serbaguna Chopper Daging Plastik Penggiling Daging Listrik 250Watt Multifungsi",
    "harga": "60,0RB",
    "link_komisi": "https://s.shopee.co.id/5q48RcGos8"
  }
]
